{"zone": "DE", "history": [{"zone": "DE", "carbonIntensity": 352, "datetime": "2025-11-04T17:00:00.000Z", "updatedAt": "2025-11-05T13:26:54.661Z", "createdAt": "2025-11-02T00:42:36.709Z", "emissionFactorType": "lifecycle", "isEstimated": false, "estimationMethod": null}, {"zone": "DE", "carbonIntensity": 337, "datetime": "2025-11-04T18:00:00.000Z", "updatedAt": "2025-11-05T13:26:31.001Z", "createdAt": "2025-11-02T00:43:18.293Z", "emissionFactorType": "lifecycle", "isEstimated": false, "estimationMethod": null}, {"zone": "DE", "carbonIntensity": 320, "datetime": "2025-11-04T19:00:00.000Z", "updatedAt": "2025-11-05T10:25:01.974Z", "createdAt": "2025-11-02T00:42:36.709Z", "emissionFactorType": "lifecycle", "isEstimated": false, "estimationMethod": null}, {"zone": "DE", "carbonIntensity": 303, "datetime": "2025-11-04T20:00:00.000Z", "updatedAt": "2025-11-04T23:56:31.169Z", "createdAt": "2025-11-02T00:43:18.293Z", "emissionFactorType": "lifecycle", "isEstimated": false, "estimationMethod": null}, {"zone": "DE", "carbonIntensity": 300, "datetime": "2025-11-04T21:00:00.000Z", "updatedAt": "2025-11-05T00:40:03.799Z", "createdAt": "2025-11-02T00:42:45.580Z", "emissionFactorType": "lifecycle", "isEstimated": false, "estimationMethod": null}, {"zone": "DE", "carbonIntensity": 284, "datetime": "2025-11-04T22:00:00.000Z", "updatedAt": "2025-11-05T10:25:15.443Z", "createdAt": "2025-11-02T00:43:18.293Z", "emissionFactorType": "lifecycle", "isEstimated": false, "estimationMethod": null}, {"zone": "DE", "carbonIntensity": 264, "datetime": "2025-11-04T23:00:00.000Z", "updatedAt": "2025-11-05T02:42:33.877Z", "createdAt": "2025-11-02T00:42:45.580Z", "emissionFactorType": "lifecycle", "isEstimated": false, "estimationMethod": null}, {"zone": "DE", "carbonIntensity": 253, "datetime": "2025-11-05T00:00:00.000Z", "updatedAt": "2025-11-05T04:11:38.333Z", "createdAt": "2025-11-02T00:42:36.709Z", "emissionFactorType": "lifecycle", "isEstimated": false, "estimationMethod": null}, {"zone": "DE", "carbonIntensity": 258, "datetime": "2025-11-05T01:00:00.000Z", "updatedAt": "2025-11-05T04:41:04.217Z", "createdAt": "2025-11-03T00:25:23.774Z", "emissionFactorType": "lifecycle", "isEstimated": false, "estimationMethod": null}, {"zone": "DE", "carbonIntensity": 268, "datetime": "2025-11-05T02:00:00.000Z", "updatedAt": "2025-11-05T05:40:52.103Z", "createdAt": "2025-11-03T00:25:13.790Z", "emissionFactorType": "lifecycle", "isEstimated": false, "estimationMethod": null}, {"zone": "DE", "carbonIntensity": 286, "datetime": "2025-11-05T03:00:00.000Z", "updatedAt": "2025-11-05T07:09:59.110Z", "createdAt": "2025-11-03T01:10:33.973Z", "emissionFactorType": "lifecycle", "isEstimated": false, "estimationMethod": null}, {"zone": "DE", "carbonIntensity": 310, "datetime": "2025-11-05T04:00:00.000Z", "updatedAt": "2025-11-05T09:40:12.500Z", "createdAt": "2025-11-03T01:10:33.973Z", "emissionFactorType": "lifecycle", "isEstimated": false, "estimationMethod": null}, {"zone": "DE", "carbonIntensity": 325, "datetime": "2025-11-05T05:00:00.000Z", "updatedAt": "2025-11-05T09:40:12.500Z", "createdAt": "2025-11-03T01:10:33.973Z", "emissionFactorType": "lifecycle", "isEstimated": false, "estimationMethod": null}, {"zone": "DE", "carbonIntensity": 341, "datetime": "2025-11-05T06:00:00.000Z", "updatedAt": "2025-11-05T10:40:19.247Z", "createdAt": "2025-11-03T01:10:42.302Z", "emissionFactorType": "lifecycle", "isEstimated": false, "estimationMethod": null}, {"zone": "DE", "carbonIntensity": 308, "datetime": "2025-11-05T07:00:00.000Z", "updatedAt": "2025-11-05T12:40:34.192Z", "createdAt": "2025-11-03T01:10:42.302Z", "emissionFactorType": "lifecycle", "isEstimated": false, "estimationMethod": null}, {"zone": "DE", "carbonIntensity": 253, "datetime": "2025-11-05T08:00:00.000Z", "updatedAt": "2025-11-05T12:40:34.192Z", "createdAt": "2025-11-03T01:10:22.213Z", "emissionFactorType": "lifecycle", "isEstimated": false, "estimationMethod": null}, {"zone": "DE", "carbonIntensity": 238, "datetime": "2025-11-05T09:00:00.000Z", "updatedAt": "2025-11-05T12:40:19.582Z", "createdAt": "2025-11-03T01:10:42.302Z", "emissionFactorType": "lifecycle", "isEstimated": false, "estimationMethod": null}, {"zone": "DE", "carbonIntensity": 247, "datetime": "2025-11-05T10:00:00.000Z", "updatedAt": "2025-11-05T13:41:15.665Z", "createdAt": "2025-11-03T01:10:22.213Z", "emissionFactorType": "lifecycle", "isEstimated": false, "estimationMethod": null}, {"zone": "DE", "carbonIntensity": 258, "datetime": "2025-11-05T11:00:00.000Z", "updatedAt": "2025-11-05T14:41:40.589Z", "createdAt": "2025-11-03T01:10:42.302Z", "emissionFactorType": "lifecycle", "isEstimated": false, "estimationMethod": null}, {"zone": "DE", "carbonIntensity": 301, "datetime": "2025-11-05T12:00:00.000Z", "updatedAt": "2025-11-05T15:40:46.024Z", "createdAt": "2025-11-03T01:10:33.973Z", "emissionFactorType": "lifecycle", "isEstimated": false, "estimationMethod": null}, {"zone": "DE", "carbonIntensity": 356, "datetime": "2025-11-05T13:00:00.000Z", "updatedAt": "2025-11-05T16:25:20.983Z", "createdAt": "2025-11-03T01:10:42.302Z", "emissionFactorType": "lifecycle", "isEstimated": false, "estimationMethod": null}, {"zone": "DE", "carbonIntensity": 421, "datetime": "2025-11-05T14:00:00.000Z", "updatedAt": "2025-11-05T16:25:20.983Z", "createdAt": "2025-11-03T01:10:42.302Z", "emissionFactorType": "lifecycle", "isEstimated": false, "estimationMethod": null}, {"zone": "DE", "carbonIntensity": 441, "datetime": "2025-11-05T15:00:00.000Z", "updatedAt": "2025-11-05T16:25:35.292Z", "createdAt": "2025-11-03T01:10:22.213Z", "emissionFactorType": "lifecycle", "isEstimated": true, "estimationMethod": "FORECASTS_HIERARCHY"}, {"zone": "DE", "carbonIntensity": 456, "datetime": "2025-11-05T16:00:00.000Z", "updatedAt": "2025-11-05T16:25:20.983Z", "createdAt": "2025-11-03T01:10:42.302Z", "emissionFactorType": "lifecycle", "isEstimated": true, "estimationMethod": "FORECASTS_HIERARCHY"}], "temporalGranularity": "hourly"}