{"zone": "DE", "history": [{"zone": "DE", "datetime": "2025-10-04T17:00:00.000Z", "updatedAt": "2025-10-05T10:40:53.716Z", "createdAt": "2025-10-02T00:09:49.381Z", "powerConsumptionBreakdown": {"nuclear": 829, "geothermal": 17, "biomass": 4111, "coal": 2229, "wind": 39849, "solar": 13, "hydro": 1240, "gas": 2260, "oil": 229, "unknown": 155, "hydro discharge": 2399, "battery discharge": 0}, "powerProductionBreakdown": {"nuclear": null, "geothermal": 20, "biomass": 4953, "coal": 2701, "wind": 47786, "solar": 0, "hydro": 1376, "gas": 2724, "oil": 275, "unknown": 188, "hydro discharge": 2893, "battery discharge": null}, "powerImportBreakdown": {"AT": 0, "BE": 0, "CH": 0, "CZ": 0, "FR": 1707, "LU": 0, "NL": 0, "PL": 0, "DK-DK1": 0, "DK-DK2": 0, "NO-NO2": 0, "SE-SE4": 0}, "powerExportBreakdown": {"AT": 1284, "BE": 857, "CH": 1462, "CZ": 1729, "FR": 0, "LU": 447, "NL": 896, "PL": 1568, "DK-DK1": 2017, "DK-DK2": 678, "NO-NO2": 166, "SE-SE4": 190}, "fossilFreePercentage": 91, "renewablePercentage": 89, "powerConsumptionTotal": 53331, "powerProductionTotal": 62917, "powerImportTotal": 1707, "powerExportTotal": 11292, "isEstimated": false, "estimationMethod": null}, {"zone": "DE", "datetime": "2025-10-04T18:00:00.000Z", "updatedAt": "2025-10-05T10:10:48.169Z", "createdAt": "2025-10-02T00:09:34.641Z", "powerConsumptionBreakdown": {"nuclear": 632, "geothermal": 16, "biomass": 3994, "coal": 2310, "wind": 39025, "solar": 1, "hydro": 1169, "gas": 2015, "oil": 222, "unknown": 151, "hydro discharge": 1331, "battery discharge": 0}, "powerProductionBreakdown": {"nuclear": null, "geothermal": 20, "biomass": 4959, "coal": 2881, "wind": 48299, "solar": 0, "hydro": 1366, "gas": 2502, "oil": 275, "unknown": 188, "hydro discharge": 1656, "battery discharge": null}, "powerImportBreakdown": {"AT": 0, "BE": 0, "CH": 0, "CZ": 0, "FR": 1306, "LU": 0, "NL": 0, "PL": 0, "DK-DK1": 0, "DK-DK2": 0, "NO-NO2": 0, "SE-SE4": 0}, "powerExportBreakdown": {"AT": 1485, "BE": 792, "CH": 1677, "CZ": 1589, "FR": 0, "LU": 315, "NL": 1294, "PL": 1485, "DK-DK1": 2372, "DK-DK2": 723, "NO-NO2": 356, "SE-SE4": 499}, "fossilFreePercentage": 91, "renewablePercentage": 90, "powerConsumptionTotal": 50864, "powerProductionTotal": 62145, "powerImportTotal": 1306, "powerExportTotal": 12586, "isEstimated": false, "estimationMethod": null}, {"zone": "DE", "datetime": "2025-10-04T19:00:00.000Z", "updatedAt": "2025-10-05T10:10:48.169Z", "createdAt": "2025-10-02T00:10:01.131Z", "powerConsumptionBreakdown": {"nuclear": 668, "geothermal": 16, "biomass": 3968, "coal": 2250, "wind": 36816, "solar": 0, "hydro": 1440, "gas": 1897, "oil": 221, "unknown": 150, "hydro discharge": 997, "battery discharge": 0}, "powerProductionBreakdown": {"nuclear": null, "geothermal": 20, "biomass": 4944, "coal": 2817, "wind": 45597, "solar": 0, "hydro": 1361, "gas": 2362, "oil": 275, "unknown": 188, "hydro discharge": 1255, "battery discharge": null}, "powerImportBreakdown": {"AT": 0, "BE": 0, "CH": 0, "CZ": 0, "FR": 1357, "LU": 0, "NL": 0, "PL": 0, "DK-DK1": 0, "DK-DK2": 0, "NO-NO2": 546, "SE-SE4": 0}, "powerExportBreakdown": {"AT": 1560, "BE": 606, "CH": 1793, "CZ": 1529, "FR": 0, "LU": 308, "NL": 1198, "PL": 1727, "DK-DK1": 2331, "DK-DK2": 740, "NO-NO2": 0, "SE-SE4": 506}, "fossilFreePercentage": 91, "renewablePercentage": 89, "powerConsumptionTotal": 48425, "powerProductionTotal": 58820, "powerImportTotal": 1903, "powerExportTotal": 12298, "isEstimated": false, "estimationMethod": null}, {"zone": "DE", "datetime": "2025-10-04T20:00:00.000Z", "updatedAt": "2025-10-05T10:11:17.399Z", "createdAt": "2025-10-02T00:09:34.641Z", "powerConsumptionBreakdown": {"nuclear": 753, "geothermal": 16, "biomass": 3829, "coal": 2161, "wind": 34650, "solar": 0, "hydro": 1526, "gas": 1896, "oil": 218, "unknown": 149, "hydro discharge": 654, "battery discharge": 0}, "powerProductionBreakdown": {"nuclear": null, "geothermal": 20, "biomass": 4839, "coal": 2748, "wind": 43442, "solar": 0, "hydro": 1352, "gas": 2386, "oil": 275, "unknown": 188, "hydro discharge": 789, "battery discharge": null}, "powerImportBreakdown": {"AT": 0, "BE": 0, "CH": 0, "CZ": 0, "FR": 1573, "LU": 0, "NL": 0, "PL": 0, "DK-DK1": 0, "DK-DK2": 0, "NO-NO2": 784, "SE-SE4": 0}, "powerExportBreakdown": {"AT": 1735, "BE": 710, "CH": 1825, "CZ": 1664, "FR": 0, "LU": 195, "NL": 878, "PL": 1916, "DK-DK1": 2382, "DK-DK2": 734, "NO-NO2": 0, "SE-SE4": 506}, "fossilFreePercentage": 90, "renewablePercentage": 89, "powerConsumptionTotal": 45850, "powerProductionTotal": 56039, "powerImportTotal": 2357, "powerExportTotal": 12545, "isEstimated": false, "estimationMethod": null}, {"zone": "DE", "datetime": "2025-10-04T21:00:00.000Z", "updatedAt": "2025-10-05T10:10:48.169Z", "createdAt": "2025-10-02T00:09:49.381Z", "powerConsumptionBreakdown": {"nuclear": 726, "geothermal": 15, "biomass": 3741, "coal": 2069, "wind": 33615, "solar": 0, "hydro": 1437, "gas": 1835, "oil": 213, "unknown": 145, "hydro discharge": 0, "battery discharge": 0}, "powerProductionBreakdown": {"nuclear": null, "geothermal": 20, "biomass": 4841, "coal": 2694, "wind": 43150, "solar": 0, "hydro": 1301, "gas": 2365, "oil": 275, "unknown": 188, "hydro discharge": -1698, "battery discharge": null}, "powerImportBreakdown": {"AT": 0, "BE": 0, "CH": 0, "CZ": 0, "FR": 1563, "LU": 0, "NL": 0, "PL": 0, "DK-DK1": 0, "DK-DK2": 0, "NO-NO2": 787, "SE-SE4": 0}, "powerExportBreakdown": {"AT": 1622, "BE": 775, "CH": 1860, "CZ": 1335, "FR": 0, "LU": 117, "NL": 921, "PL": 1447, "DK-DK1": 2405, "DK-DK2": 702, "NO-NO2": 0, "SE-SE4": 506}, "fossilFreePercentage": 90, "renewablePercentage": 89, "powerConsumptionTotal": 43798, "powerProductionTotal": 54834, "powerImportTotal": 2350, "powerExportTotal": 11688, "isEstimated": false, "estimationMethod": null}, {"zone": "DE", "datetime": "2025-10-04T22:00:00.000Z", "updatedAt": "2025-10-05T08:41:17.949Z", "createdAt": "2025-10-02T00:09:49.381Z", "powerConsumptionBreakdown": {"nuclear": 749, "geothermal": 15, "biomass": 3662, "coal": 2041, "wind": 31820, "solar": 0, "hydro": 1273, "gas": 1892, "oil": 212, "unknown": 143, "hydro discharge": 0, "battery discharge": 0}, "powerProductionBreakdown": {"nuclear": null, "geothermal": 20, "biomass": 4824, "coal": 2707, "wind": 41525, "solar": 0, "hydro": 1303, "gas": 2481, "oil": 279, "unknown": 188, "hydro discharge": -2634, "battery discharge": null}, "powerImportBreakdown": {"AT": 0, "BE": 0, "CH": 0, "CZ": 0, "FR": 1631, "LU": 0, "NL": 0, "PL": 0, "DK-DK1": 0, "DK-DK2": 0, "NO-NO2": 621, "SE-SE4": 0}, "powerExportBreakdown": {"AT": 1806, "BE": 890, "CH": 1762, "CZ": 1056, "FR": 0, "LU": 66, "NL": 416, "PL": 1448, "DK-DK1": 2463, "DK-DK2": 725, "NO-NO2": 0, "SE-SE4": 506}, "fossilFreePercentage": 90, "renewablePercentage": 88, "powerConsumptionTotal": 41807, "powerProductionTotal": 53326, "powerImportTotal": 2251, "powerExportTotal": 11136, "isEstimated": false, "estimationMethod": null}, {"zone": "DE", "datetime": "2025-10-04T23:00:00.000Z", "updatedAt": "2025-10-05T08:41:35.101Z", "createdAt": "2025-10-02T00:09:34.641Z", "powerConsumptionBreakdown": {"nuclear": 805, "geothermal": 15, "biomass": 3559, "coal": 1967, "wind": 30210, "solar": 0, "hydro": 1367, "gas": 1850, "oil": 208, "unknown": 141, "hydro discharge": 0, "battery discharge": 0}, "powerProductionBreakdown": {"nuclear": null, "geothermal": 20, "biomass": 4780, "coal": 2664, "wind": 40145, "solar": 0, "hydro": 1470, "gas": 2466, "oil": 279, "unknown": 188, "hydro discharge": -3633, "battery discharge": null}, "powerImportBreakdown": {"AT": 0, "BE": 0, "CH": 0, "CZ": 0, "FR": 1747, "LU": 0, "NL": 0, "PL": 0, "DK-DK1": 0, "DK-DK2": 0, "NO-NO2": 691, "SE-SE4": 0}, "powerExportBreakdown": {"AT": 1828, "BE": 886, "CH": 1620, "CZ": 1050, "FR": 0, "LU": 50, "NL": 277, "PL": 1389, "DK-DK1": 2368, "DK-DK2": 721, "NO-NO2": 0, "SE-SE4": 506}, "fossilFreePercentage": 90, "renewablePercentage": 88, "powerConsumptionTotal": 40122, "powerProductionTotal": 52011, "powerImportTotal": 2438, "powerExportTotal": 10693, "isEstimated": false, "estimationMethod": null}, {"zone": "DE", "datetime": "2025-10-05T00:00:00.000Z", "updatedAt": "2025-10-05T08:41:02.190Z", "createdAt": "2025-10-02T21:12:26.247Z", "powerConsumptionBreakdown": {"nuclear": 773, "geothermal": 15, "biomass": 3604, "coal": 2015, "wind": 29355, "solar": 0, "hydro": 1305, "gas": 1901, "oil": 213, "unknown": 144, "hydro discharge": 0, "battery discharge": 0}, "powerProductionBreakdown": {"nuclear": null, "geothermal": 20, "biomass": 4730, "coal": 2666, "wind": 38203, "solar": 0, "hydro": 1526, "gas": 2475, "oil": 280, "unknown": 188, "hydro discharge": -3712, "battery discharge": null}, "powerImportBreakdown": {"AT": 0, "BE": 0, "CH": 0, "CZ": 0, "FR": 1599, "LU": 0, "NL": 76, "PL": 0, "DK-DK1": 0, "DK-DK2": 0, "NO-NO2": 264, "SE-SE4": 0}, "powerExportBreakdown": {"AT": 1490, "BE": 688, "CH": 1419, "CZ": 637, "FR": 0, "LU": 39, "NL": 0, "PL": 1081, "DK-DK1": 2389, "DK-DK2": 738, "NO-NO2": 0, "SE-SE4": 506}, "fossilFreePercentage": 89, "renewablePercentage": 87, "powerConsumptionTotal": 39327, "powerProductionTotal": 50087, "powerImportTotal": 1939, "powerExportTotal": 8987, "isEstimated": false, "estimationMethod": null}, {"zone": "DE", "datetime": "2025-10-05T01:00:00.000Z", "updatedAt": "2025-10-05T08:41:35.101Z", "createdAt": "2025-10-02T21:11:46.978Z", "powerConsumptionBreakdown": {"nuclear": 666, "geothermal": 15, "biomass": 3508, "coal": 1997, "wind": 29318, "solar": 0, "hydro": 1314, "gas": 1879, "oil": 210, "unknown": 142, "hydro discharge": 0, "battery discharge": 0}, "powerProductionBreakdown": {"nuclear": null, "geothermal": 20, "biomass": 4671, "coal": 2677, "wind": 38786, "solar": 0, "hydro": 1455, "gas": 2478, "oil": 279, "unknown": 188, "hydro discharge": -3248, "battery discharge": null}, "powerImportBreakdown": {"AT": 0, "BE": 0, "CH": 0, "CZ": 0, "FR": 1255, "LU": 0, "NL": 0, "PL": 0, "DK-DK1": 0, "DK-DK2": 0, "NO-NO2": 637, "SE-SE4": 0}, "powerExportBreakdown": {"AT": 1724, "BE": 716, "CH": 1639, "CZ": 846, "FR": 0, "LU": 121, "NL": 223, "PL": 1327, "DK-DK1": 2319, "DK-DK2": 729, "NO-NO2": 0, "SE-SE4": 506}, "fossilFreePercentage": 89, "renewablePercentage": 87, "powerConsumptionTotal": 39049, "powerProductionTotal": 50555, "powerImportTotal": 1892, "powerExportTotal": 10149, "isEstimated": false, "estimationMethod": null}, {"zone": "DE", "datetime": "2025-10-05T02:00:00.000Z", "updatedAt": "2025-10-05T08:41:02.190Z", "createdAt": "2025-10-02T21:11:46.978Z", "powerConsumptionBreakdown": {"nuclear": 731, "geothermal": 15, "biomass": 3554, "coal": 2028, "wind": 29389, "solar": 0, "hydro": 1396, "gas": 1975, "oil": 215, "unknown": 146, "hydro discharge": 0, "battery discharge": 0}, "powerProductionBreakdown": {"nuclear": null, "geothermal": 20, "biomass": 4618, "coal": 2654, "wind": 37937, "solar": 0, "hydro": 1526, "gas": 2543, "oil": 279, "unknown": 188, "hydro discharge": -1770, "battery discharge": null}, "powerImportBreakdown": {"AT": 0, "BE": 0, "CH": 0, "CZ": 0, "FR": 1346, "LU": 0, "NL": 0, "PL": 0, "DK-DK1": 0, "DK-DK2": 0, "NO-NO2": 609, "SE-SE4": 0}, "powerExportBreakdown": {"AT": 1834, "BE": 646, "CH": 1476, "CZ": 1066, "FR": 0, "LU": 97, "NL": 367, "PL": 1384, "DK-DK1": 2386, "DK-DK2": 738, "NO-NO2": 0, "SE-SE4": 506}, "fossilFreePercentage": 89, "renewablePercentage": 87, "powerConsumptionTotal": 39449, "powerProductionTotal": 49764, "powerImportTotal": 1955, "powerExportTotal": 10500, "isEstimated": false, "estimationMethod": null}, {"zone": "DE", "datetime": "2025-10-05T03:00:00.000Z", "updatedAt": "2025-10-05T08:41:02.190Z", "createdAt": "2025-10-02T21:12:26.247Z", "powerConsumptionBreakdown": {"nuclear": 664, "geothermal": 15, "biomass": 3544, "coal": 2044, "wind": 29159, "solar": 0, "hydro": 1449, "gas": 1998, "oil": 216, "unknown": 147, "hydro discharge": 0, "battery discharge": 0}, "powerProductionBreakdown": {"nuclear": null, "geothermal": 20, "biomass": 4585, "coal": 2663, "wind": 37442, "solar": 0, "hydro": 1573, "gas": 2560, "oil": 279, "unknown": 188, "hydro discharge": -1624, "battery discharge": null}, "powerImportBreakdown": {"AT": 0, "BE": 0, "CH": 0, "CZ": 0, "FR": 1225, "LU": 0, "NL": 0, "PL": 0, "DK-DK1": 0, "DK-DK2": 0, "NO-NO2": 675, "SE-SE4": 0}, "powerExportBreakdown": {"AT": 1838, "BE": 542, "CH": 1440, "CZ": 1113, "FR": 0, "LU": 68, "NL": 270, "PL": 1504, "DK-DK1": 2328, "DK-DK2": 739, "NO-NO2": 0, "SE-SE4": 506}, "fossilFreePercentage": 89, "renewablePercentage": 87, "powerConsumptionTotal": 39237, "powerProductionTotal": 49309, "powerImportTotal": 1900, "powerExportTotal": 10347, "isEstimated": false, "estimationMethod": null}, {"zone": "DE", "datetime": "2025-10-05T04:00:00.000Z", "updatedAt": "2025-10-05T08:41:17.949Z", "createdAt": "2025-10-02T21:11:55.226Z", "powerConsumptionBreakdown": {"nuclear": 793, "geothermal": 16, "biomass": 3607, "coal": 2071, "wind": 29969, "solar": 0, "hydro": 1404, "gas": 2037, "oil": 219, "unknown": 149, "hydro discharge": 0, "battery discharge": 0}, "powerProductionBreakdown": {"nuclear": null, "geothermal": 20, "biomass": 4606, "coal": 2665, "wind": 37799, "solar": 0, "hydro": 1441, "gas": 2568, "oil": 279, "unknown": 188, "hydro discharge": -2181, "battery discharge": null}, "powerImportBreakdown": {"AT": 0, "BE": 0, "CH": 0, "CZ": 0, "FR": 1493, "LU": 0, "NL": 0, "PL": 0, "DK-DK1": 0, "DK-DK2": 0, "NO-NO2": 810, "SE-SE4": 0}, "powerExportBreakdown": {"AT": 1634, "BE": 149, "CH": 1147, "CZ": 1086, "FR": 0, "LU": 57, "NL": 378, "PL": 1500, "DK-DK1": 2225, "DK-DK2": 740, "NO-NO2": 0, "SE-SE4": 506}, "fossilFreePercentage": 89, "renewablePercentage": 87, "powerConsumptionTotal": 40266, "powerProductionTotal": 49566, "powerImportTotal": 2304, "powerExportTotal": 9422, "isEstimated": false, "estimationMethod": null}, {"zone": "DE", "datetime": "2025-10-05T05:00:00.000Z", "updatedAt": "2025-10-05T08:41:35.101Z", "createdAt": "2025-10-02T21:11:55.226Z", "powerConsumptionBreakdown": {"nuclear": 720, "geothermal": 16, "biomass": 3706, "coal": 2126, "wind": 31546, "solar": 233, "hydro": 1457, "gas": 1966, "oil": 224, "unknown": 152, "hydro discharge": 0, "battery discharge": 0}, "powerProductionBreakdown": {"nuclear": null, "geothermal": 20, "biomass": 4631, "coal": 2675, "wind": 38964, "solar": 294, "hydro": 1494, "gas": 2430, "oil": 279, "unknown": 188, "hydro discharge": -1211, "battery discharge": null}, "powerImportBreakdown": {"AT": 0, "BE": 0, "CH": 0, "CZ": 0, "FR": 1411, "LU": 0, "NL": 0, "PL": 0, "DK-DK1": 0, "DK-DK2": 0, "NO-NO2": 748, "SE-SE4": 0}, "powerExportBreakdown": {"AT": 1660, "BE": 550, "CH": 1327, "CZ": 1194, "FR": 0, "LU": 54, "NL": 447, "PL": 1317, "DK-DK1": 1988, "DK-DK2": 734, "NO-NO2": 0, "SE-SE4": 506}, "fossilFreePercentage": 89, "renewablePercentage": 88, "powerConsumptionTotal": 42145, "powerProductionTotal": 50974, "powerImportTotal": 2159, "powerExportTotal": 9776, "isEstimated": false, "estimationMethod": null}, {"zone": "DE", "datetime": "2025-10-05T06:00:00.000Z", "updatedAt": "2025-10-05T09:40:35.072Z", "createdAt": "2025-10-02T21:12:26.247Z", "powerConsumptionBreakdown": {"nuclear": 563, "geothermal": 16, "biomass": 3693, "coal": 2109, "wind": 32150, "solar": 2537, "hydro": 1394, "gas": 1939, "oil": 221, "unknown": 152, "hydro discharge": 0, "battery discharge": 0}, "powerProductionBreakdown": {"nuclear": null, "geothermal": 20, "biomass": 4663, "coal": 2677, "wind": 40171, "solar": 3227, "hydro": 1437, "gas": 2424, "oil": 279, "unknown": 188, "hydro discharge": -1436, "battery discharge": null}, "powerImportBreakdown": {"AT": 0, "BE": 0, "CH": 0, "CZ": 0, "FR": 1123, "LU": 0, "NL": 0, "PL": 0, "DK-DK1": 0, "DK-DK2": 0, "NO-NO2": 767, "SE-SE4": 0}, "powerExportBreakdown": {"AT": 1911, "BE": 722, "CH": 1661, "CZ": 1286, "FR": 0, "LU": 98, "NL": 836, "PL": 1139, "DK-DK1": 1872, "DK-DK2": 735, "NO-NO2": 0, "SE-SE4": 506}, "fossilFreePercentage": 90, "renewablePercentage": 89, "powerConsumptionTotal": 44774, "powerProductionTotal": 55085, "powerImportTotal": 1890, "powerExportTotal": 10764, "isEstimated": false, "estimationMethod": null}, {"zone": "DE", "datetime": "2025-10-05T07:00:00.000Z", "updatedAt": "2025-10-05T11:11:30.130Z", "createdAt": "2025-10-02T21:11:46.978Z", "powerConsumptionBreakdown": {"nuclear": 584, "geothermal": 16, "biomass": 3736, "coal": 2137, "wind": 31372, "solar": 6614, "hydro": 1440, "gas": 2034, "oil": 224, "unknown": 151, "hydro discharge": 0, "battery discharge": 0}, "powerProductionBreakdown": {"nuclear": null, "geothermal": 20, "biomass": 4676, "coal": 2688, "wind": 38846, "solar": 8249, "hydro": 1460, "gas": 2527, "oil": 279, "unknown": 188, "hydro discharge": -2572, "battery discharge": null}, "powerImportBreakdown": {"AT": 0, "BE": 0, "CH": 0, "CZ": 0, "FR": 1231, "LU": 0, "NL": 0, "PL": 0, "DK-DK1": 0, "DK-DK2": 0, "NO-NO2": 762, "SE-SE4": 0}, "powerExportBreakdown": {"AT": 1812, "BE": 547, "CH": 1060, "CZ": 1307, "FR": 0, "LU": 127, "NL": 683, "PL": 1243, "DK-DK1": 2035, "DK-DK2": 726, "NO-NO2": 0, "SE-SE4": 506}, "fossilFreePercentage": 91, "renewablePercentage": 89, "powerConsumptionTotal": 48308, "powerProductionTotal": 58933, "powerImportTotal": 1993, "powerExportTotal": 10045, "isEstimated": false, "estimationMethod": null}, {"zone": "DE", "datetime": "2025-10-05T08:00:00.000Z", "updatedAt": "2025-10-05T11:40:40.264Z", "createdAt": "2025-10-02T21:11:55.226Z", "powerConsumptionBreakdown": {"nuclear": 459, "geothermal": 16, "biomass": 3731, "coal": 2124, "wind": 30458, "solar": 10274, "hydro": 1512, "gas": 2066, "oil": 223, "unknown": 153, "hydro discharge": 0, "battery discharge": 0}, "powerProductionBreakdown": {"nuclear": null, "geothermal": 20, "biomass": 4675, "coal": 2671, "wind": 37849, "solar": 12773, "hydro": 1542, "gas": 2565, "oil": 279, "unknown": 188, "hydro discharge": -3087, "battery discharge": null}, "powerImportBreakdown": {"AT": 0, "BE": 0, "CH": 0, "CZ": 0, "FR": 980, "LU": 0, "NL": 0, "PL": 0, "DK-DK1": 0, "DK-DK2": 0, "NO-NO2": 795, "SE-SE4": 0}, "powerExportBreakdown": {"AT": 1875, "BE": 903, "CH": 718, "CZ": 1592, "FR": 0, "LU": 200, "NL": 190, "PL": 1427, "DK-DK1": 2103, "DK-DK2": 721, "NO-NO2": 0, "SE-SE4": 506}, "fossilFreePercentage": 91, "renewablePercentage": 90, "powerConsumptionTotal": 51016, "powerProductionTotal": 62561, "powerImportTotal": 1775, "powerExportTotal": 10234, "isEstimated": false, "estimationMethod": null}, {"zone": "DE", "datetime": "2025-10-05T09:00:00.000Z", "updatedAt": "2025-10-05T12:40:29.597Z", "createdAt": "2025-10-02T21:12:26.247Z", "powerConsumptionBreakdown": {"nuclear": 376, "geothermal": 16, "biomass": 3818, "coal": 2153, "wind": 30220, "solar": 13020, "hydro": 1485, "gas": 2147, "oil": 227, "unknown": 155, "hydro discharge": 0, "battery discharge": 1}, "powerProductionBreakdown": {"nuclear": null, "geothermal": 20, "biomass": 4714, "coal": 2668, "wind": 37048, "solar": 15912, "hydro": 1527, "gas": 2621, "oil": 280, "unknown": 188, "hydro discharge": -3827, "battery discharge": null}, "powerImportBreakdown": {"AT": 0, "BE": 0, "CH": 0, "CZ": 0, "FR": 808, "LU": 0, "NL": 137, "PL": 0, "DK-DK1": 0, "DK-DK2": 0, "NO-NO2": 700, "SE-SE4": 0}, "powerExportBreakdown": {"AT": 1583, "BE": 927, "CH": 130, "CZ": 1544, "FR": 0, "LU": 267, "NL": 0, "PL": 1445, "DK-DK1": 2124, "DK-DK2": 650, "NO-NO2": 0, "SE-SE4": 506}, "fossilFreePercentage": 91, "renewablePercentage": 91, "powerConsumptionTotal": 53618, "powerProductionTotal": 64977, "powerImportTotal": 1644, "powerExportTotal": 9176, "isEstimated": false, "estimationMethod": null}, {"zone": "DE", "datetime": "2025-10-05T10:00:00.000Z", "updatedAt": "2025-10-05T13:42:49.773Z", "createdAt": "2025-10-02T21:11:55.226Z", "powerConsumptionBreakdown": {"nuclear": 54, "geothermal": 16, "biomass": 3707, "coal": 2108, "wind": 29694, "solar": 14314, "hydro": 1405, "gas": 2001, "oil": 219, "unknown": 149, "hydro discharge": 0, "battery discharge": 0}, "powerProductionBreakdown": {"nuclear": null, "geothermal": 20, "biomass": 4722, "coal": 2685, "wind": 37582, "solar": 18192, "hydro": 1527, "gas": 2534, "oil": 279, "unknown": 188, "hydro discharge": -4105, "battery discharge": null}, "powerImportBreakdown": {"AT": 0, "BE": 0, "CH": 0, "CZ": 0, "FR": 0, "LU": 0, "NL": 0, "PL": 0, "DK-DK1": 0, "DK-DK2": 0, "NO-NO2": 716, "SE-SE4": 0}, "powerExportBreakdown": {"AT": 1600, "BE": 727, "CH": 993, "CZ": 1651, "FR": 176, "LU": 465, "NL": 632, "PL": 1527, "DK-DK1": 2010, "DK-DK2": 386, "NO-NO2": 0, "SE-SE4": 506}, "fossilFreePercentage": 92, "renewablePercentage": 92, "powerConsumptionTotal": 53668, "powerProductionTotal": 67729, "powerImportTotal": 716, "powerExportTotal": 10672, "isEstimated": false, "estimationMethod": null}, {"zone": "DE", "datetime": "2025-10-05T11:00:00.000Z", "updatedAt": "2025-10-05T15:10:54.445Z", "createdAt": "2025-10-02T21:11:55.226Z", "powerConsumptionBreakdown": {"nuclear": 6, "geothermal": 15, "biomass": 3614, "coal": 2036, "wind": 28643, "solar": 13869, "hydro": 1207, "gas": 1900, "oil": 213, "unknown": 144, "hydro discharge": 0, "battery discharge": 0}, "powerProductionBreakdown": {"nuclear": null, "geothermal": 20, "biomass": 4737, "coal": 2668, "wind": 37404, "solar": 18164, "hydro": 1440, "gas": 2484, "oil": 279, "unknown": 188, "hydro discharge": -3961, "battery discharge": null}, "powerImportBreakdown": {"AT": 0, "BE": 0, "CH": 0, "CZ": 0, "FR": 0, "LU": 0, "NL": 0, "PL": 0, "DK-DK1": 0, "DK-DK2": 0, "NO-NO2": 408, "SE-SE4": 0}, "powerExportBreakdown": {"AT": 1961, "BE": 852, "CH": 1495, "CZ": 1773, "FR": 406, "LU": 410, "NL": 346, "PL": 1668, "DK-DK1": 2351, "DK-DK2": 418, "NO-NO2": 0, "SE-SE4": 506}, "fossilFreePercentage": 92, "renewablePercentage": 92, "powerConsumptionTotal": 51646, "powerProductionTotal": 67385, "powerImportTotal": 408, "powerExportTotal": 12185, "isEstimated": false, "estimationMethod": null}, {"zone": "DE", "datetime": "2025-10-05T12:00:00.000Z", "updatedAt": "2025-10-05T15:39:22.610Z", "createdAt": "2025-10-02T21:11:46.978Z", "powerConsumptionBreakdown": {"nuclear": 10, "geothermal": 15, "biomass": 3575, "coal": 2016, "wind": 28133, "solar": 12834, "hydro": 1336, "gas": 1888, "oil": 212, "unknown": 144, "hydro discharge": 0, "battery discharge": 0}, "powerProductionBreakdown": {"nuclear": null, "geothermal": 20, "biomass": 4707, "coal": 2653, "wind": 36768, "solar": 16880, "hydro": 1472, "gas": 2476, "oil": 279, "unknown": 188, "hydro discharge": -3993, "battery discharge": null}, "powerImportBreakdown": {"AT": 0, "BE": 0, "CH": 0, "CZ": 0, "FR": 0, "LU": 0, "NL": 0, "PL": 0, "DK-DK1": 0, "DK-DK2": 0, "NO-NO2": 792, "SE-SE4": 0}, "powerExportBreakdown": {"AT": 2063, "BE": 846, "CH": 1202, "CZ": 1778, "FR": 266, "LU": 362, "NL": 497, "PL": 1720, "DK-DK1": 2255, "DK-DK2": 578, "NO-NO2": 0, "SE-SE4": 511}, "fossilFreePercentage": 92, "renewablePercentage": 91, "powerConsumptionTotal": 50163, "powerProductionTotal": 65443, "powerImportTotal": 792, "powerExportTotal": 12078, "isEstimated": false, "estimationMethod": null}, {"zone": "DE", "datetime": "2025-10-05T13:00:00.000Z", "updatedAt": "2025-10-05T15:39:22.610Z", "createdAt": "2025-10-02T21:11:46.978Z", "powerConsumptionBreakdown": {"nuclear": 177, "geothermal": 16, "biomass": 3672, "coal": 2127, "wind": 29194, "solar": 11223, "hydro": 1286, "gas": 1980, "oil": 221, "unknown": 148, "hydro discharge": 0, "battery discharge": 0}, "powerProductionBreakdown": {"nuclear": null, "geothermal": 20, "biomass": 4658, "coal": 2702, "wind": 36939, "solar": 14175, "hydro": 1475, "gas": 2506, "oil": 280, "unknown": 188, "hydro discharge": -3317, "battery discharge": null}, "powerImportBreakdown": {"AT": 0, "BE": 0, "CH": 0, "CZ": 0, "FR": 394, "LU": 0, "NL": 0, "PL": 0, "DK-DK1": 0, "DK-DK2": 0, "NO-NO2": 346, "SE-SE4": 0}, "powerExportBreakdown": {"AT": 1986, "BE": 845, "CH": 961, "CZ": 1747, "FR": 0, "LU": 111, "NL": 188, "PL": 1251, "DK-DK1": 2125, "DK-DK2": 594, "NO-NO2": 0, "SE-SE4": 516}, "fossilFreePercentage": 91, "renewablePercentage": 91, "powerConsumptionTotal": 50043, "powerProductionTotal": 62943, "powerImportTotal": 740, "powerExportTotal": 10323, "isEstimated": false, "estimationMethod": null}, {"zone": "DE", "datetime": "2025-10-05T14:00:00.000Z", "updatedAt": "2025-10-05T15:39:44.964Z", "createdAt": "2025-10-02T21:11:55.226Z", "powerConsumptionBreakdown": {"nuclear": 572, "geothermal": 16, "biomass": 3665, "coal": 2090, "wind": 28406, "solar": 9173, "hydro": 1221, "gas": 1984, "oil": 219, "unknown": 147, "hydro discharge": 0, "battery discharge": 0}, "powerProductionBreakdown": {"nuclear": null, "geothermal": 20, "biomass": 4672, "coal": 2679, "wind": 36230, "solar": 11524, "hydro": 1462, "gas": 2524, "oil": 279, "unknown": 188, "hydro discharge": -3731, "battery discharge": null}, "powerImportBreakdown": {"AT": 0, "BE": 0, "CH": 0, "CZ": 0, "FR": 1251, "LU": 0, "NL": 0, "PL": 0, "DK-DK1": 0, "DK-DK2": 0, "NO-NO2": 0, "SE-SE4": 0}, "powerExportBreakdown": {"AT": 1986, "BE": 298, "CH": 564, "CZ": 1849, "FR": 0, "LU": 45, "NL": 188, "PL": 1251, "DK-DK1": 2148, "DK-DK2": 709, "NO-NO2": 48, "SE-SE4": 517}, "fossilFreePercentage": 91, "renewablePercentage": 89, "powerConsumptionTotal": 47494, "powerProductionTotal": 59577, "powerImportTotal": 1251, "powerExportTotal": 9602, "isEstimated": true, "estimationMethod": "FORECASTS_HIERARCHY"}, {"zone": "DE", "datetime": "2025-10-05T15:00:00.000Z", "updatedAt": "2025-10-05T15:39:33.652Z", "createdAt": "2025-10-02T21:11:46.978Z", "powerConsumptionBreakdown": {"nuclear": 724, "geothermal": 17, "biomass": 3978, "coal": 3231, "wind": 33156, "solar": 5732, "hydro": 1606, "gas": 3747, "oil": 237, "unknown": 162, "hydro discharge": 0, "battery discharge": 0}, "powerProductionBreakdown": {"nuclear": null, "geothermal": 20, "biomass": 4692, "coal": 3835, "wind": 38950, "solar": 6510, "hydro": 1520, "gas": 4422, "oil": 279, "unknown": 190, "hydro discharge": -1261, "battery discharge": null}, "powerImportBreakdown": {"AT": 0, "BE": 0, "CH": 0, "CZ": 0, "FR": 1452, "LU": 0, "NL": 0, "PL": 0, "DK-DK1": 0, "DK-DK2": 0, "NO-NO2": 637, "SE-SE4": 0}, "powerExportBreakdown": {"AT": 1236, "BE": 680, "CH": 61, "CZ": 1767, "FR": 0, "LU": 161, "NL": 69, "PL": 1149, "DK-DK1": 2202, "DK-DK2": 718, "NO-NO2": 0, "SE-SE4": 612}, "fossilFreePercentage": 86, "renewablePercentage": 85, "powerConsumptionTotal": 52590, "powerProductionTotal": 60418, "powerImportTotal": 2089, "powerExportTotal": 8656, "isEstimated": true, "estimationMethod": "FORECASTS_HIERARCHY"}, {"zone": "DE", "datetime": "2025-10-05T16:00:00.000Z", "updatedAt": "2025-10-05T15:39:22.610Z", "createdAt": "2025-10-02T21:12:26.247Z", "powerConsumptionBreakdown": {"nuclear": 723, "geothermal": 18, "biomass": 4185, "coal": 3847, "wind": 34948, "solar": 1556, "hydro": 1789, "gas": 4818, "oil": 271, "unknown": 178, "hydro discharge": 720, "battery discharge": 0}, "powerProductionBreakdown": {"nuclear": null, "geothermal": 20, "biomass": 4752, "coal": 4392, "wind": 39564, "solar": 1621, "hydro": 1598, "gas": 5462, "oil": 303, "unknown": 191, "hydro discharge": 821, "battery discharge": null}, "powerImportBreakdown": {"AT": 0, "BE": 0, "CH": 195, "CZ": 0, "FR": 1254, "LU": 0, "NL": 30, "PL": 0, "DK-DK1": 0, "DK-DK2": 0, "NO-NO2": 435, "SE-SE4": 0}, "powerExportBreakdown": {"AT": 711, "BE": 665, "CH": 0, "CZ": 1425, "FR": 0, "LU": 277, "NL": 0, "PL": 1067, "DK-DK1": 2379, "DK-DK2": 527, "NO-NO2": 0, "SE-SE4": 534}, "fossilFreePercentage": 83, "renewablePercentage": 81, "powerConsumptionTotal": 53053, "powerProductionTotal": 58724, "powerImportTotal": 1914, "powerExportTotal": 7585, "isEstimated": true, "estimationMethod": "FORECASTS_HIERARCHY"}], "temporalGranularity": "hourly"}