{"zone": "FR", "history": [{"zone": "FR", "datetime": "2025-04-13T17:00:00.000Z", "updatedAt": "2025-04-14T09:46:19.981Z", "createdAt": "2025-04-10T17:43:19.221Z", "powerConsumptionBreakdown": {"nuclear": 31953, "geothermal": 0, "biomass": 798, "coal": 11, "wind": 2007, "solar": 1717, "hydro": 5083, "gas": 752, "oil": 393, "unknown": 4, "hydro discharge": 749, "battery discharge": 0}, "powerProductionBreakdown": {"nuclear": 40431, "geothermal": null, "biomass": 982, "coal": 0, "wind": 2311, "solar": 1658, "hydro": 6167, "gas": 750, "oil": 503, "unknown": null, "hydro discharge": 962, "battery discharge": -2}, "powerImportBreakdown": {"BE": 0, "CH": 0, "DE": 0, "ES": 1765, "GB": 0, "IT-NO": 0}, "powerExportBreakdown": {"BE": 1384, "CH": 1683, "DE": 2442, "ES": 0, "GB": 2994, "IT-NO": 3555}, "fossilFreePercentage": 97, "renewablePercentage": 24, "powerConsumptionTotal": 43468, "powerProductionTotal": 53763, "powerImportTotal": 1765, "powerExportTotal": 12058, "isEstimated": false, "estimationMethod": null}, {"zone": "FR", "datetime": "2025-04-13T18:00:00.000Z", "updatedAt": "2025-04-14T13:48:28.625Z", "createdAt": "2025-04-10T18:43:28.752Z", "powerConsumptionBreakdown": {"nuclear": 32825, "geothermal": 0, "biomass": 794, "coal": 9, "wind": 1654, "solar": 461, "hydro": 5409, "gas": 835, "oil": 641, "unknown": 4, "hydro discharge": 1747, "battery discharge": 0}, "powerProductionBreakdown": {"nuclear": 41833, "geothermal": null, "biomass": 983, "coal": 0, "wind": 1921, "solar": 443, "hydro": 6507, "gas": 803, "oil": 823, "unknown": null, "hydro discharge": 2154, "battery discharge": -17}, "powerImportBreakdown": {"BE": 0, "CH": 0, "DE": 0, "ES": 1564, "GB": 0, "IT-NO": 0}, "powerExportBreakdown": {"BE": 1540, "CH": 1796, "DE": 2664, "ES": 0, "GB": 2992, "IT-NO": 3643}, "fossilFreePercentage": 97, "renewablePercentage": 23, "powerConsumptionTotal": 44378, "powerProductionTotal": 55466, "powerImportTotal": 1564, "powerExportTotal": 12635, "isEstimated": false, "estimationMethod": null}, {"zone": "FR", "datetime": "2025-04-13T19:00:00.000Z", "updatedAt": "2025-04-14T09:46:40.238Z", "createdAt": "2025-04-10T19:41:33.333Z", "powerConsumptionBreakdown": {"nuclear": 33667, "geothermal": 0, "biomass": 757, "coal": 2, "wind": 1470, "solar": 53, "hydro": 5510, "gas": 562, "oil": 500, "unknown": 1, "hydro discharge": 1951, "battery discharge": 0}, "powerProductionBreakdown": {"nuclear": 42887, "geothermal": null, "biomass": 957, "coal": 0, "wind": 1823, "solar": 61, "hydro": 6910, "gas": 633, "oil": 639, "unknown": null, "hydro discharge": 2446, "battery discharge": -11}, "powerImportBreakdown": {"BE": 0, "CH": 0, "DE": 0, "ES": 254, "GB": 0, "IT-NO": 0}, "powerExportBreakdown": {"BE": 1031, "CH": 1896, "DE": 2344, "ES": 0, "GB": 2977, "IT-NO": 3878}, "fossilFreePercentage": 98, "renewablePercentage": 22, "powerConsumptionTotal": 44472, "powerProductionTotal": 56355, "powerImportTotal": 254, "powerExportTotal": 12125, "isEstimated": false, "estimationMethod": null}, {"zone": "FR", "datetime": "2025-04-13T20:00:00.000Z", "updatedAt": "2025-04-14T09:46:45.937Z", "createdAt": "2025-04-10T20:41:29.109Z", "powerConsumptionBreakdown": {"nuclear": 33561, "geothermal": 0, "biomass": 752, "coal": 4, "wind": 1602, "solar": 5, "hydro": 5597, "gas": 509, "oil": 62, "unknown": 2, "hydro discharge": 1905, "battery discharge": 0}, "powerProductionBreakdown": {"nuclear": 43170, "geothermal": null, "biomass": 953, "coal": 0, "wind": 1956, "solar": 0, "hydro": 6994, "gas": 502, "oil": 80, "unknown": null, "hydro discharge": 2374, "battery discharge": -15}, "powerImportBreakdown": {"BE": 0, "CH": 0, "DE": 0, "ES": 559, "GB": 0, "IT-NO": 0}, "powerExportBreakdown": {"BE": 1375, "CH": 2167, "DE": 2299, "ES": 0, "GB": 2621, "IT-NO": 4107}, "fossilFreePercentage": 99, "renewablePercentage": 22, "powerConsumptionTotal": 44002, "powerProductionTotal": 56027, "powerImportTotal": 559, "powerExportTotal": 12569, "isEstimated": false, "estimationMethod": null}, {"zone": "FR", "datetime": "2025-04-13T21:00:00.000Z", "updatedAt": "2025-04-14T10:43:42.333Z", "createdAt": "2025-04-10T21:43:29.825Z", "powerConsumptionBreakdown": {"nuclear": 33951, "geothermal": 0, "biomass": 776, "coal": 8, "wind": 1822, "solar": 8, "hydro": 5537, "gas": 633, "oil": 64, "unknown": 4, "hydro discharge": 1769, "battery discharge": 0}, "powerProductionBreakdown": {"nuclear": 42910, "geothermal": null, "biomass": 953, "coal": 0, "wind": 2122, "solar": 0, "hydro": 6578, "gas": 491, "oil": 81, "unknown": null, "hydro discharge": 2119, "battery discharge": -7}, "powerImportBreakdown": {"BE": 0, "CH": 0, "DE": 0, "ES": 1533, "GB": 0, "IT-NO": 0}, "powerExportBreakdown": {"BE": 1275, "CH": 2015, "DE": 2100, "ES": 0, "GB": 2955, "IT-NO": 3860}, "fossilFreePercentage": 98, "renewablePercentage": 22, "powerConsumptionTotal": 44573, "powerProductionTotal": 55252, "powerImportTotal": 1533, "powerExportTotal": 12205, "isEstimated": false, "estimationMethod": null}, {"zone": "FR", "datetime": "2025-04-13T22:00:00.000Z", "updatedAt": "2025-04-14T09:46:45.937Z", "createdAt": "2025-04-10T22:42:14.111Z", "powerConsumptionBreakdown": {"nuclear": 33480, "geothermal": 0, "biomass": 751, "coal": 5, "wind": 1811, "solar": 5, "hydro": 4789, "gas": 495, "oil": 63, "unknown": 3, "hydro discharge": 1243, "battery discharge": 3}, "powerProductionBreakdown": {"nuclear": 42881, "geothermal": null, "biomass": 946, "coal": 0, "wind": 2231, "solar": 0, "hydro": 5897, "gas": 448, "oil": 80, "unknown": null, "hydro discharge": 1543, "battery discharge": 4}, "powerImportBreakdown": {"BE": 0, "CH": 0, "DE": 0, "ES": 878, "GB": 0, "IT-NO": 0}, "powerExportBreakdown": {"BE": 1195, "CH": 2207, "DE": 2132, "ES": 0, "GB": 2991, "IT-NO": 3735}, "fossilFreePercentage": 99, "renewablePercentage": 20, "powerConsumptionTotal": 42647, "powerProductionTotal": 54029, "powerImportTotal": 878, "powerExportTotal": 12260, "isEstimated": false, "estimationMethod": null}, {"zone": "FR", "datetime": "2025-04-13T23:00:00.000Z", "updatedAt": "2025-04-14T09:46:19.981Z", "createdAt": "2025-04-10T23:41:44.476Z", "powerConsumptionBreakdown": {"nuclear": 32118, "geothermal": 0, "biomass": 730, "coal": 5, "wind": 1548, "solar": 3, "hydro": 4352, "gas": 436, "oil": 61, "unknown": 2, "hydro discharge": 813, "battery discharge": 1}, "powerProductionBreakdown": {"nuclear": 42236, "geothermal": null, "biomass": 945, "coal": 0, "wind": 1967, "solar": 0, "hydro": 5507, "gas": 404, "oil": 81, "unknown": null, "hydro discharge": 1032, "battery discharge": 0}, "powerImportBreakdown": {"BE": 0, "CH": 0, "DE": 0, "ES": 779, "GB": 0, "IT-NO": 0}, "powerExportBreakdown": {"BE": 1674, "CH": 2344, "DE": 2180, "ES": 0, "GB": 2994, "IT-NO": 3688}, "fossilFreePercentage": 99, "renewablePercentage": 19, "powerConsumptionTotal": 40069, "powerProductionTotal": 52171, "powerImportTotal": 779, "powerExportTotal": 12880, "isEstimated": false, "estimationMethod": null}, {"zone": "FR", "datetime": "2025-04-14T00:00:00.000Z", "updatedAt": "2025-04-14T12:48:08.572Z", "createdAt": "2025-04-11T00:44:11.709Z", "powerConsumptionBreakdown": {"nuclear": 31865, "geothermal": 0, "biomass": 728, "coal": 6, "wind": 1284, "solar": 2, "hydro": 4194, "gas": 419, "oil": 61, "unknown": 2, "hydro discharge": 511, "battery discharge": 1}, "powerProductionBreakdown": {"nuclear": 42131, "geothermal": null, "biomass": 950, "coal": 0, "wind": 1642, "solar": 0, "hydro": 5363, "gas": 405, "oil": 81, "unknown": null, "hydro discharge": 650, "battery discharge": -3}, "powerImportBreakdown": {"BE": 0, "CH": 0, "DE": 0, "ES": 665, "GB": 0, "IT-NO": 0}, "powerExportBreakdown": {"BE": 1945, "CH": 2139, "DE": 2256, "ES": 0, "GB": 2993, "IT-NO": 3478}, "fossilFreePercentage": 99, "renewablePercentage": 17, "powerConsumptionTotal": 39073, "powerProductionTotal": 51221, "powerImportTotal": 665, "powerExportTotal": 12811, "isEstimated": false, "estimationMethod": null}, {"zone": "FR", "datetime": "2025-04-14T01:00:00.000Z", "updatedAt": "2025-04-14T09:46:40.238Z", "createdAt": "2025-04-11T01:46:45.187Z", "powerConsumptionBreakdown": {"nuclear": 31417, "geothermal": 0, "biomass": 714, "coal": 0, "wind": 960, "solar": 0, "hydro": 3827, "gas": 303, "oil": 60, "unknown": 0, "hydro discharge": 297, "battery discharge": 0}, "powerProductionBreakdown": {"nuclear": 41896, "geothermal": null, "biomass": 952, "coal": 0, "wind": 1281, "solar": 0, "hydro": 5104, "gas": 405, "oil": 80, "unknown": null, "hydro discharge": 397, "battery discharge": -4}, "powerImportBreakdown": {"BE": 0, "CH": 0, "DE": 0, "ES": 0, "GB": 0, "IT-NO": 0}, "powerExportBreakdown": {"BE": 2093, "CH": 1907, "DE": 2100, "ES": 87, "GB": 2992, "IT-NO": 3353}, "fossilFreePercentage": 99, "renewablePercentage": 15, "powerConsumptionTotal": 37579, "powerProductionTotal": 50114, "powerImportTotal": 0, "powerExportTotal": 12531, "isEstimated": false, "estimationMethod": null}, {"zone": "FR", "datetime": "2025-04-14T02:00:00.000Z", "updatedAt": "2025-04-14T09:46:40.238Z", "createdAt": "2025-04-11T02:44:06.353Z", "powerConsumptionBreakdown": {"nuclear": 31250, "geothermal": 0, "biomass": 727, "coal": 0, "wind": 786, "solar": 0, "hydro": 3795, "gas": 304, "oil": 60, "unknown": 0, "hydro discharge": 16, "battery discharge": 0}, "powerProductionBreakdown": {"nuclear": 41672, "geothermal": null, "biomass": 969, "coal": 0, "wind": 1049, "solar": 0, "hydro": 5061, "gas": 405, "oil": 80, "unknown": null, "hydro discharge": -1, "battery discharge": -4}, "powerImportBreakdown": {"BE": 0, "CH": 0, "DE": 0, "ES": 0, "GB": 0, "IT-NO": 0}, "powerExportBreakdown": {"BE": 1733, "CH": 2053, "DE": 1855, "ES": 154, "GB": 2990, "IT-NO": 3508}, "fossilFreePercentage": 99, "renewablePercentage": 14, "powerConsumptionTotal": 36938, "powerProductionTotal": 49236, "powerImportTotal": 0, "powerExportTotal": 12293, "isEstimated": false, "estimationMethod": null}, {"zone": "FR", "datetime": "2025-04-14T03:00:00.000Z", "updatedAt": "2025-04-14T09:46:40.238Z", "createdAt": "2025-04-11T03:44:50.403Z", "powerConsumptionBreakdown": {"nuclear": 32229, "geothermal": 0, "biomass": 754, "coal": 4, "wind": 777, "solar": 3, "hydro": 4087, "gas": 410, "oil": 62, "unknown": 2, "hydro discharge": 444, "battery discharge": 0}, "powerProductionBreakdown": {"nuclear": 42162, "geothermal": null, "biomass": 974, "coal": 0, "wind": 931, "solar": 0, "hydro": 5200, "gas": 405, "oil": 81, "unknown": null, "hydro discharge": 590, "battery discharge": -4}, "powerImportBreakdown": {"BE": 0, "CH": 0, "DE": 0, "ES": 589, "GB": 0, "IT-NO": 0}, "powerExportBreakdown": {"BE": 1564, "CH": 2124, "DE": 2050, "ES": 0, "GB": 2990, "IT-NO": 3425}, "fossilFreePercentage": 99, "renewablePercentage": 16, "powerConsumptionTotal": 38772, "powerProductionTotal": 50340, "powerImportTotal": 589, "powerExportTotal": 12154, "isEstimated": false, "estimationMethod": null}, {"zone": "FR", "datetime": "2025-04-14T04:00:00.000Z", "updatedAt": "2025-04-14T11:45:16.521Z", "createdAt": "2025-04-11T04:42:58.337Z", "powerConsumptionBreakdown": {"nuclear": 33885, "geothermal": 0, "biomass": 807, "coal": 10, "wind": 932, "solar": 102, "hydro": 5355, "gas": 632, "oil": 64, "unknown": 6, "hydro discharge": 1609, "battery discharge": 0}, "powerProductionBreakdown": {"nuclear": 42445, "geothermal": null, "biomass": 973, "coal": 0, "wind": 878, "solar": 124, "hydro": 6198, "gas": 404, "oil": 81, "unknown": null, "hydro discharge": 1983, "battery discharge": -5}, "powerImportBreakdown": {"BE": 0, "CH": 0, "DE": 0, "ES": 1874, "GB": 0, "IT-NO": 0}, "powerExportBreakdown": {"BE": 1893, "CH": 1154, "DE": 2368, "ES": 0, "GB": 2991, "IT-NO": 3146}, "fossilFreePercentage": 98, "renewablePercentage": 20, "powerConsumptionTotal": 43402, "powerProductionTotal": 53085, "powerImportTotal": 1874, "powerExportTotal": 11552, "isEstimated": false, "estimationMethod": null}, {"zone": "FR", "datetime": "2025-04-14T05:00:00.000Z", "updatedAt": "2025-04-14T12:48:21.847Z", "createdAt": "2025-04-11T05:43:27.693Z", "powerConsumptionBreakdown": {"nuclear": 35954, "geothermal": 0, "biomass": 834, "coal": 13, "wind": 990, "solar": 391, "hydro": 6454, "gas": 617, "oil": 68, "unknown": 5, "hydro discharge": 2264, "battery discharge": 0}, "powerProductionBreakdown": {"nuclear": 43046, "geothermal": null, "biomass": 971, "coal": 0, "wind": 956, "solar": 468, "hydro": 7344, "gas": 453, "oil": 81, "unknown": null, "hydro discharge": 2609, "battery discharge": -7}, "powerImportBreakdown": {"BE": 0, "CH": 0, "DE": 0, "ES": 1471, "GB": 0, "IT-NO": 0}, "powerExportBreakdown": {"BE": 1585, "CH": 415, "DE": 2287, "ES": 0, "GB": 2990, "IT-NO": 2526}, "fossilFreePercentage": 99, "renewablePercentage": 23, "powerConsumptionTotal": 47588, "powerProductionTotal": 55927, "powerImportTotal": 1471, "powerExportTotal": 9803, "isEstimated": false, "estimationMethod": null}, {"zone": "FR", "datetime": "2025-04-14T06:00:00.000Z", "updatedAt": "2025-04-14T12:47:56.393Z", "createdAt": "2025-04-11T06:44:41.198Z", "powerConsumptionBreakdown": {"nuclear": 36821, "geothermal": 0, "biomass": 835, "coal": 13, "wind": 1190, "solar": 1581, "hydro": 6474, "gas": 597, "oil": 68, "unknown": 4, "hydro discharge": 2558, "battery discharge": 0}, "powerProductionBreakdown": {"nuclear": 43679, "geothermal": null, "biomass": 968, "coal": 0, "wind": 1211, "solar": 1849, "hydro": 7327, "gas": 459, "oil": 81, "unknown": null, "hydro discharge": 2943, "battery discharge": -4}, "powerImportBreakdown": {"BE": 0, "CH": 0, "DE": 0, "ES": 1337, "GB": 0, "IT-NO": 0}, "powerExportBreakdown": {"BE": 1492, "CH": 497, "DE": 1905, "ES": 0, "GB": 2992, "IT-NO": 2820}, "fossilFreePercentage": 99, "renewablePercentage": 25, "powerConsumptionTotal": 50141, "powerProductionTotal": 58515, "powerImportTotal": 1337, "powerExportTotal": 9706, "isEstimated": false, "estimationMethod": null}, {"zone": "FR", "datetime": "2025-04-14T07:00:00.000Z", "updatedAt": "2025-04-14T12:48:08.572Z", "createdAt": "2025-04-11T07:44:16.131Z", "powerConsumptionBreakdown": {"nuclear": 36552, "geothermal": 0, "biomass": 826, "coal": 7, "wind": 1282, "solar": 4166, "hydro": 5864, "gas": 515, "oil": 68, "unknown": 3, "hydro discharge": 1353, "battery discharge": 0}, "powerProductionBreakdown": {"nuclear": 43545, "geothermal": null, "biomass": 969, "coal": 0, "wind": 1364, "solar": 4836, "hydro": 6747, "gas": 460, "oil": 81, "unknown": null, "hydro discharge": 1566, "battery discharge": -14}, "powerImportBreakdown": {"BE": 0, "CH": 0, "DE": 0, "ES": 1043, "GB": 0, "IT-NO": 0}, "powerExportBreakdown": {"BE": 1191, "CH": 1361, "DE": 1365, "ES": 0, "GB": 2992, "IT-NO": 3049}, "fossilFreePercentage": 99, "renewablePercentage": 27, "powerConsumptionTotal": 50636, "powerProductionTotal": 59565, "powerImportTotal": 1043, "powerExportTotal": 9958, "isEstimated": false, "estimationMethod": null}, {"zone": "FR", "datetime": "2025-04-14T08:00:00.000Z", "updatedAt": "2025-04-14T10:43:46.802Z", "createdAt": "2025-04-11T08:42:27.051Z", "powerConsumptionBreakdown": {"nuclear": 35412, "geothermal": 0, "biomass": 815, "coal": 6, "wind": 1376, "solar": 6472, "hydro": 5023, "gas": 464, "oil": 67, "unknown": 2, "hydro discharge": 79, "battery discharge": 0}, "powerProductionBreakdown": {"nuclear": 42690, "geothermal": null, "biomass": 968, "coal": 0, "wind": 1480, "solar": 7584, "hydro": 5874, "gas": 445, "oil": 81, "unknown": null, "hydro discharge": -177, "battery discharge": -30}, "powerImportBreakdown": {"BE": 0, "CH": 0, "DE": 0, "ES": 994, "GB": 0, "IT-NO": 0}, "powerExportBreakdown": {"BE": 1125, "CH": 1813, "DE": 1178, "ES": 0, "GB": 2992, "IT-NO": 3086}, "fossilFreePercentage": 99, "renewablePercentage": 28, "powerConsumptionTotal": 49717, "powerProductionTotal": 59122, "powerImportTotal": 994, "powerExportTotal": 10194, "isEstimated": false, "estimationMethod": null}, {"zone": "FR", "datetime": "2025-04-14T09:00:00.000Z", "updatedAt": "2025-04-14T11:44:51.021Z", "createdAt": "2025-04-11T09:44:21.356Z", "powerConsumptionBreakdown": {"nuclear": 33548, "geothermal": 0, "biomass": 805, "coal": 8, "wind": 1811, "solar": 8334, "hydro": 4385, "gas": 459, "oil": 65, "unknown": 3, "hydro discharge": 0, "battery discharge": 0}, "powerProductionBreakdown": {"nuclear": 41097, "geothermal": null, "biomass": 969, "coal": 0, "wind": 1955, "solar": 9786, "hydro": 5215, "gas": 412, "oil": 80, "unknown": null, "hydro discharge": -1449, "battery discharge": -19}, "powerImportBreakdown": {"BE": 0, "CH": 0, "DE": 0, "ES": 1408, "GB": 0, "IT-NO": 0}, "powerExportBreakdown": {"BE": 1280, "CH": 1889, "DE": 800, "ES": 0, "GB": 2993, "IT-NO": 3073}, "fossilFreePercentage": 99, "renewablePercentage": 31, "powerConsumptionTotal": 49418, "powerProductionTotal": 59513, "powerImportTotal": 1408, "powerExportTotal": 10035, "isEstimated": false, "estimationMethod": null}, {"zone": "FR", "datetime": "2025-04-14T10:00:00.000Z", "updatedAt": "2025-04-14T12:48:08.572Z", "createdAt": "2025-04-11T10:44:58.403Z", "powerConsumptionBreakdown": {"nuclear": 33593, "geothermal": 0, "biomass": 811, "coal": 6, "wind": 2150, "solar": 9523, "hydro": 4194, "gas": 412, "oil": 66, "unknown": 2, "hydro discharge": 0, "battery discharge": 2}, "powerProductionBreakdown": {"nuclear": 40592, "geothermal": null, "biomass": 969, "coal": 0, "wind": 2390, "solar": 11146, "hydro": 4990, "gas": 407, "oil": 80, "unknown": null, "hydro discharge": -1060, "battery discharge": -9}, "powerImportBreakdown": {"BE": 0, "CH": 0, "DE": 0, "ES": 1030, "GB": 0, "IT-NO": 0}, "powerExportBreakdown": {"BE": 1376, "CH": 1633, "DE": 906, "ES": 0, "GB": 2993, "IT-NO": 2868}, "fossilFreePercentage": 99, "renewablePercentage": 33, "powerConsumptionTotal": 50759, "powerProductionTotal": 60574, "powerImportTotal": 1030, "powerExportTotal": 9776, "isEstimated": false, "estimationMethod": null}, {"zone": "FR", "datetime": "2025-04-14T11:00:00.000Z", "updatedAt": "2025-04-14T13:48:28.625Z", "createdAt": "2025-04-11T11:43:37.470Z", "powerConsumptionBreakdown": {"nuclear": 32302, "geothermal": 0, "biomass": 808, "coal": 2, "wind": 2172, "solar": 9490, "hydro": 3988, "gas": 361, "oil": 67, "unknown": 1, "hydro discharge": 0, "battery discharge": 16}, "powerProductionBreakdown": {"nuclear": 38957, "geothermal": null, "biomass": 971, "coal": 0, "wind": 2549, "solar": 11322, "hydro": 4788, "gas": 407, "oil": 81, "unknown": null, "hydro discharge": -1606, "battery discharge": 19}, "powerImportBreakdown": {"BE": 0, "CH": 0, "DE": 0, "ES": 332, "GB": 0, "IT-NO": 0}, "powerExportBreakdown": {"BE": 895, "CH": 1369, "DE": 748, "ES": 0, "GB": 2994, "IT-NO": 2606}, "fossilFreePercentage": 99, "renewablePercentage": 33, "powerConsumptionTotal": 49208, "powerProductionTotal": 59094, "powerImportTotal": 332, "powerExportTotal": 8611, "isEstimated": false, "estimationMethod": null}, {"zone": "FR", "datetime": "2025-04-14T12:00:00.000Z", "updatedAt": "2025-04-14T14:41:03.304Z", "createdAt": "2025-04-11T12:42:53.518Z", "powerConsumptionBreakdown": {"nuclear": 30930, "geothermal": 0, "biomass": 797, "coal": 3, "wind": 2544, "solar": 9074, "hydro": 3884, "gas": 363, "oil": 66, "unknown": 1, "hydro discharge": 0, "battery discharge": 21}, "powerProductionBreakdown": {"nuclear": 37975, "geothermal": null, "biomass": 974, "coal": 0, "wind": 3034, "solar": 10989, "hydro": 4737, "gas": 408, "oil": 81, "unknown": null, "hydro discharge": -1893, "battery discharge": 26}, "powerImportBreakdown": {"BE": 0, "CH": 0, "DE": 0, "ES": 442, "GB": 0, "IT-NO": 0}, "powerExportBreakdown": {"BE": 1103, "CH": 1427, "DE": 941, "ES": 0, "GB": 2992, "IT-NO": 2626}, "fossilFreePercentage": 99, "renewablePercentage": 34, "powerConsumptionTotal": 47683, "powerProductionTotal": 58222, "powerImportTotal": 442, "powerExportTotal": 9089, "isEstimated": false, "estimationMethod": null}, {"zone": "FR", "datetime": "2025-04-14T13:00:00.000Z", "updatedAt": "2025-04-14T15:43:22.470Z", "createdAt": "2025-04-11T13:42:50.586Z", "powerConsumptionBreakdown": {"nuclear": 30300, "geothermal": 0, "biomass": 793, "coal": 2, "wind": 2612, "solar": 8439, "hydro": 4118, "gas": 357, "oil": 66, "unknown": 1, "hydro discharge": 0, "battery discharge": 11}, "powerProductionBreakdown": {"nuclear": 37279, "geothermal": null, "biomass": 972, "coal": 0, "wind": 3137, "solar": 10261, "hydro": 5041, "gas": 407, "oil": 81, "unknown": null, "hydro discharge": -2086, "battery discharge": 14}, "powerImportBreakdown": {"BE": 0, "CH": 0, "DE": 0, "ES": 367, "GB": 0, "IT-NO": 0}, "powerExportBreakdown": {"BE": 1231, "CH": 1201, "DE": 753, "ES": 0, "GB": 2994, "IT-NO": 2595}, "fossilFreePercentage": 99, "renewablePercentage": 34, "powerConsumptionTotal": 46698, "powerProductionTotal": 57191, "powerImportTotal": 367, "powerExportTotal": 8774, "isEstimated": false, "estimationMethod": null}, {"zone": "FR", "datetime": "2025-04-14T14:00:00.000Z", "updatedAt": "2025-04-14T15:43:22.470Z", "createdAt": "2025-04-11T14:46:31.987Z", "powerConsumptionBreakdown": {"nuclear": 30584, "geothermal": 0, "biomass": 789, "coal": 3, "wind": 2527, "solar": 7518, "hydro": 4375, "gas": 364, "oil": 65, "unknown": 1, "hydro discharge": 0, "battery discharge": 0}, "powerProductionBreakdown": {"nuclear": 37772, "geothermal": null, "biomass": 969, "coal": 0, "wind": 3021, "solar": 9123, "hydro": 5370, "gas": 408, "oil": 81, "unknown": null, "hydro discharge": -1890, "battery discharge": -11}, "powerImportBreakdown": {"BE": 0, "CH": 0, "DE": 0, "ES": 451, "GB": 0, "IT-NO": 0}, "powerExportBreakdown": {"BE": 1585, "CH": 1201, "DE": 753, "ES": 0, "GB": 2993, "IT-NO": 2534}, "fossilFreePercentage": 99, "renewablePercentage": 33, "powerConsumptionTotal": 46227, "powerProductionTotal": 56743, "powerImportTotal": 451, "powerExportTotal": 9066, "isEstimated": false, "estimationMethod": null}, {"zone": "FR", "datetime": "2025-04-14T15:00:00.000Z", "updatedAt": "2025-04-14T15:43:22.470Z", "createdAt": "2025-04-11T15:43:32.625Z", "powerConsumptionBreakdown": {"nuclear": 30058, "geothermal": 0, "biomass": 773, "coal": 1, "wind": 2450, "solar": 7325, "hydro": 4289, "gas": 343, "oil": 64, "unknown": 1, "hydro discharge": 0, "battery discharge": 0}, "powerProductionBreakdown": {"nuclear": 37772, "geothermal": null, "biomass": 969, "coal": 0, "wind": 3021, "solar": 9123, "hydro": 5370, "gas": 408, "oil": 81, "unknown": null, "hydro discharge": -1890, "battery discharge": -11}, "powerImportBreakdown": {"BE": 0, "CH": 0, "DE": 0, "ES": 260, "GB": 0, "IT-NO": 0}, "powerExportBreakdown": {"BE": 1528, "CH": 1518, "DE": 1222, "ES": 0, "GB": 2993, "IT-NO": 2534}, "fossilFreePercentage": 99, "renewablePercentage": 33, "powerConsumptionTotal": 45305, "powerProductionTotal": 56743, "powerImportTotal": 260, "powerExportTotal": 9795, "isEstimated": true, "estimationMethod": "TIME_SLICER_AVERAGE"}, {"zone": "FR", "datetime": "2025-04-14T16:00:00.000Z", "updatedAt": "2025-04-14T15:42:58.865Z", "createdAt": "2025-04-11T16:42:36.405Z", "powerConsumptionBreakdown": {"nuclear": 32345, "geothermal": 0, "biomass": 802, "coal": 5, "wind": 3261, "solar": 5023, "hydro": 5106, "gas": 423, "oil": 66, "unknown": 2, "hydro discharge": 0, "battery discharge": 0}, "powerProductionBreakdown": {"nuclear": 39664, "geothermal": null, "biomass": 972, "coal": 0, "wind": 3763, "solar": 5885, "hydro": 6153, "gas": 422, "oil": 81, "unknown": null, "hydro discharge": -571, "battery discharge": -19}, "powerImportBreakdown": {"BE": 0, "CH": 0, "DE": 0, "ES": 989, "GB": 0, "IT-NO": 0}, "powerExportBreakdown": {"BE": 1799, "CH": 1229, "DE": 1606, "ES": 0, "GB": 3045, "IT-NO": 2626}, "fossilFreePercentage": 99, "renewablePercentage": 30, "powerConsumptionTotal": 47032, "powerProductionTotal": 56939, "powerImportTotal": 989, "powerExportTotal": 10305, "isEstimated": true, "estimationMethod": "TIME_SLICER_AVERAGE"}]}