{"zone": "FR", "history": [{"zone": "FR", "datetime": "2025-04-15T17:00:00.000Z", "updatedAt": "2025-04-16T08:45:13.151Z", "createdAt": "2025-04-12T17:42:47.254Z", "powerConsumptionBreakdown": {"nuclear": 33091, "geothermal": 0, "biomass": 820, "coal": 8, "wind": 8855, "solar": 1557, "hydro": 5084, "gas": 430, "oil": 68, "unknown": 3, "hydro discharge": 1, "battery discharge": 15}, "powerProductionBreakdown": {"nuclear": 39686, "geothermal": null, "biomass": 963, "coal": 0, "wind": 10195, "solar": 1513, "hydro": 5943, "gas": 398, "oil": 81, "unknown": null, "hydro discharge": -288, "battery discharge": 19}, "powerImportBreakdown": {"BE": 0, "CH": 0, "DE": 0, "ES": 1357, "GB": 0, "IT-NO": 0}, "powerExportBreakdown": {"BE": 1648, "CH": 549, "DE": 2077, "ES": 0, "GB": 2992, "IT-NO": 2667}, "fossilFreePercentage": 99, "renewablePercentage": 33, "powerConsumptionTotal": 49932, "powerProductionTotal": 58796, "powerImportTotal": 1357, "powerExportTotal": 9933, "isEstimated": false, "estimationMethod": null}, {"zone": "FR", "datetime": "2025-04-15T18:00:00.000Z", "updatedAt": "2025-04-16T14:48:46.993Z", "createdAt": "2025-04-12T18:41:54.030Z", "powerConsumptionBreakdown": {"nuclear": 33967, "geothermal": 0, "biomass": 806, "coal": 7, "wind": 7925, "solar": 456, "hydro": 5194, "gas": 470, "oil": 67, "unknown": 3, "hydro discharge": 97, "battery discharge": 3}, "powerProductionBreakdown": {"nuclear": 41353, "geothermal": null, "biomass": 958, "coal": 0, "wind": 9179, "solar": 443, "hydro": 6059, "gas": 400, "oil": 81, "unknown": null, "hydro discharge": -31, "battery discharge": 2}, "powerImportBreakdown": {"BE": 0, "CH": 0, "DE": 0, "ES": 1376, "GB": 0, "IT-NO": 0}, "powerExportBreakdown": {"BE": 2253, "CH": 326, "DE": 2525, "ES": 0, "GB": 2992, "IT-NO": 2728}, "fossilFreePercentage": 99, "renewablePercentage": 30, "powerConsumptionTotal": 48995, "powerProductionTotal": 58474, "powerImportTotal": 1376, "powerExportTotal": 10823, "isEstimated": false, "estimationMethod": null}, {"zone": "FR", "datetime": "2025-04-15T19:00:00.000Z", "updatedAt": "2025-04-16T08:45:38.068Z", "createdAt": "2025-04-12T19:43:40.243Z", "powerConsumptionBreakdown": {"nuclear": 34300, "geothermal": 0, "biomass": 796, "coal": 2, "wind": 6631, "solar": 59, "hydro": 5422, "gas": 385, "oil": 66, "unknown": 1, "hydro discharge": 655, "battery discharge": 1}, "powerProductionBreakdown": {"nuclear": 41786, "geothermal": null, "biomass": 961, "coal": 0, "wind": 7897, "solar": 64, "hydro": 6490, "gas": 398, "oil": 81, "unknown": null, "hydro discharge": 755, "battery discharge": 0}, "powerImportBreakdown": {"BE": 0, "CH": 0, "DE": 0, "ES": 497, "GB": 0, "IT-NO": 0}, "powerExportBreakdown": {"BE": 1950, "CH": 547, "DE": 2317, "ES": 0, "GB": 2992, "IT-NO": 2803}, "fossilFreePercentage": 99, "renewablePercentage": 28, "powerConsumptionTotal": 48319, "powerProductionTotal": 58431, "powerImportTotal": 497, "powerExportTotal": 10608, "isEstimated": false, "estimationMethod": null}, {"zone": "FR", "datetime": "2025-04-15T20:00:00.000Z", "updatedAt": "2025-04-16T08:45:13.151Z", "createdAt": "2025-04-12T20:44:08.284Z", "powerConsumptionBreakdown": {"nuclear": 33951, "geothermal": 0, "biomass": 800, "coal": 3, "wind": 6393, "solar": 6, "hydro": 5371, "gas": 404, "oil": 66, "unknown": 2, "hydro discharge": 689, "battery discharge": 0}, "powerProductionBreakdown": {"nuclear": 41437, "geothermal": null, "biomass": 965, "coal": 0, "wind": 7555, "solar": 0, "hydro": 6400, "gas": 399, "oil": 80, "unknown": null, "hydro discharge": 790, "battery discharge": -5}, "powerImportBreakdown": {"BE": 0, "CH": 0, "DE": 0, "ES": 551, "GB": 0, "IT-NO": 0}, "powerExportBreakdown": {"BE": 1625, "CH": 976, "DE": 1843, "ES": 0, "GB": 2991, "IT-NO": 3051}, "fossilFreePercentage": 99, "renewablePercentage": 28, "powerConsumptionTotal": 47686, "powerProductionTotal": 57627, "powerImportTotal": 551, "powerExportTotal": 10486, "isEstimated": false, "estimationMethod": null}, {"zone": "FR", "datetime": "2025-04-15T21:00:00.000Z", "updatedAt": "2025-04-16T10:42:23.765Z", "createdAt": "2025-04-12T21:40:54.038Z", "powerConsumptionBreakdown": {"nuclear": 34349, "geothermal": 0, "biomass": 828, "coal": 8, "wind": 6622, "solar": 9, "hydro": 5361, "gas": 501, "oil": 67, "unknown": 4, "hydro discharge": 201, "battery discharge": 0}, "powerProductionBreakdown": {"nuclear": 41250, "geothermal": null, "biomass": 965, "coal": 0, "wind": 7350, "solar": 0, "hydro": 6076, "gas": 399, "oil": 80, "unknown": null, "hydro discharge": 84, "battery discharge": -13}, "powerImportBreakdown": {"BE": 0, "CH": 0, "DE": 0, "ES": 1641, "GB": 0, "IT-NO": 0}, "powerExportBreakdown": {"BE": 1312, "CH": 954, "DE": 1703, "ES": 0, "GB": 2991, "IT-NO": 2921}, "fossilFreePercentage": 99, "renewablePercentage": 27, "powerConsumptionTotal": 47950, "powerProductionTotal": 56203, "powerImportTotal": 1641, "powerExportTotal": 9881, "isEstimated": false, "estimationMethod": null}, {"zone": "FR", "datetime": "2025-04-15T22:00:00.000Z", "updatedAt": "2025-04-16T15:42:32.606Z", "createdAt": "2025-04-12T22:43:40.135Z", "powerConsumptionBreakdown": {"nuclear": 33228, "geothermal": 0, "biomass": 811, "coal": 9, "wind": 5881, "solar": 6, "hydro": 5049, "gas": 511, "oil": 65, "unknown": 5, "hydro discharge": 49, "battery discharge": 0}, "powerProductionBreakdown": {"nuclear": 40963, "geothermal": null, "biomass": 967, "coal": 0, "wind": 6569, "solar": 0, "hydro": 5840, "gas": 401, "oil": 80, "unknown": null, "hydro discharge": -714, "battery discharge": 0}, "powerImportBreakdown": {"BE": 0, "CH": 0, "DE": 0, "ES": 1777, "GB": 0, "IT-NO": 0}, "powerExportBreakdown": {"BE": 1258, "CH": 1352, "DE": 1802, "ES": 0, "GB": 2987, "IT-NO": 2870}, "fossilFreePercentage": 99, "renewablePercentage": 26, "powerConsumptionTotal": 45614, "powerProductionTotal": 54820, "powerImportTotal": 1777, "powerExportTotal": 10269, "isEstimated": false, "estimationMethod": null}, {"zone": "FR", "datetime": "2025-04-15T23:00:00.000Z", "updatedAt": "2025-04-16T15:42:52.650Z", "createdAt": "2025-04-12T23:43:22.365Z", "powerConsumptionBreakdown": {"nuclear": 31859, "geothermal": 0, "biomass": 791, "coal": 9, "wind": 5048, "solar": 5, "hydro": 4782, "gas": 506, "oil": 64, "unknown": 5, "hydro discharge": 22, "battery discharge": 1}, "powerProductionBreakdown": {"nuclear": 40328, "geothermal": null, "biomass": 968, "coal": 0, "wind": 5694, "solar": 0, "hydro": 5675, "gas": 400, "oil": 80, "unknown": null, "hydro discharge": -1669, "battery discharge": -2}, "powerImportBreakdown": {"BE": 0, "CH": 0, "DE": 0, "ES": 1746, "GB": 0, "IT-NO": 0}, "powerExportBreakdown": {"BE": 786, "CH": 1731, "DE": 1683, "ES": 0, "GB": 2991, "IT-NO": 2940}, "fossilFreePercentage": 99, "renewablePercentage": 25, "powerConsumptionTotal": 43090, "powerProductionTotal": 53146, "powerImportTotal": 1746, "powerExportTotal": 10130, "isEstimated": false, "estimationMethod": null}, {"zone": "FR", "datetime": "2025-04-16T00:00:00.000Z", "updatedAt": "2025-04-16T15:42:52.650Z", "createdAt": "2025-04-13T00:44:01.528Z", "powerConsumptionBreakdown": {"nuclear": 31603, "geothermal": 0, "biomass": 792, "coal": 9, "wind": 4286, "solar": 2, "hydro": 4725, "gas": 513, "oil": 64, "unknown": 5, "hydro discharge": 4, "battery discharge": 0}, "powerProductionBreakdown": {"nuclear": 40087, "geothermal": null, "biomass": 969, "coal": 0, "wind": 4662, "solar": 0, "hydro": 5642, "gas": 399, "oil": 80, "unknown": null, "hydro discharge": -1726, "battery discharge": -13}, "powerImportBreakdown": {"BE": 0, "CH": 0, "DE": 0, "ES": 1776, "GB": 0, "IT-NO": 0}, "powerExportBreakdown": {"BE": 552, "CH": 1870, "DE": 1528, "ES": 0, "GB": 2994, "IT-NO": 2929}, "fossilFreePercentage": 99, "renewablePercentage": 23, "powerConsumptionTotal": 42004, "powerProductionTotal": 51840, "powerImportTotal": 1776, "powerExportTotal": 9873, "isEstimated": false, "estimationMethod": null}, {"zone": "FR", "datetime": "2025-04-16T01:00:00.000Z", "updatedAt": "2025-04-16T15:42:32.606Z", "createdAt": "2025-04-13T01:42:44.288Z", "powerConsumptionBreakdown": {"nuclear": 30265, "geothermal": 0, "biomass": 777, "coal": 11, "wind": 3791, "solar": 0, "hydro": 4581, "gas": 506, "oil": 63, "unknown": 5, "hydro discharge": 0, "battery discharge": 9}, "powerProductionBreakdown": {"nuclear": 39277, "geothermal": null, "biomass": 971, "coal": 0, "wind": 4076, "solar": 0, "hydro": 5601, "gas": 400, "oil": 81, "unknown": null, "hydro discharge": -2100, "battery discharge": 12}, "powerImportBreakdown": {"BE": 0, "CH": 0, "DE": 0, "ES": 1816, "GB": 0, "IT-NO": 0}, "powerExportBreakdown": {"BE": 377, "CH": 2050, "DE": 1723, "ES": 0, "GB": 2991, "IT-NO": 2985}, "fossilFreePercentage": 99, "renewablePercentage": 23, "powerConsumptionTotal": 40008, "powerProductionTotal": 50417, "powerImportTotal": 1816, "powerExportTotal": 10126, "isEstimated": false, "estimationMethod": null}, {"zone": "FR", "datetime": "2025-04-16T02:00:00.000Z", "updatedAt": "2025-04-16T15:42:32.606Z", "createdAt": "2025-04-13T02:41:54.275Z", "powerConsumptionBreakdown": {"nuclear": 29952, "geothermal": 0, "biomass": 777, "coal": 12, "wind": 3416, "solar": 0, "hydro": 4607, "gas": 523, "oil": 62, "unknown": 8, "hydro discharge": 0, "battery discharge": 8}, "powerProductionBreakdown": {"nuclear": 38897, "geothermal": null, "biomass": 970, "coal": 0, "wind": 3592, "solar": 0, "hydro": 5643, "gas": 401, "oil": 81, "unknown": null, "hydro discharge": -2342, "battery discharge": 11}, "powerImportBreakdown": {"BE": 89, "CH": 0, "DE": 0, "ES": 1746, "GB": 0, "IT-NO": 0}, "powerExportBreakdown": {"BE": 0, "CH": 2003, "DE": 1755, "ES": 0, "GB": 2983, "IT-NO": 2981}, "fossilFreePercentage": 98, "renewablePercentage": 22, "powerConsumptionTotal": 39365, "powerProductionTotal": 49594, "powerImportTotal": 1835, "powerExportTotal": 9722, "isEstimated": false, "estimationMethod": null}, {"zone": "FR", "datetime": "2025-04-16T03:00:00.000Z", "updatedAt": "2025-04-16T15:42:57.967Z", "createdAt": "2025-04-13T03:40:54.284Z", "powerConsumptionBreakdown": {"nuclear": 31112, "geothermal": 0, "biomass": 786, "coal": 13, "wind": 3634, "solar": 0, "hydro": 4769, "gas": 548, "oil": 63, "unknown": 13, "hydro discharge": 0, "battery discharge": 1}, "powerProductionBreakdown": {"nuclear": 39743, "geothermal": null, "biomass": 962, "coal": 0, "wind": 3784, "solar": 0, "hydro": 5766, "gas": 400, "oil": 81, "unknown": null, "hydro discharge": -2180, "battery discharge": -26}, "powerImportBreakdown": {"BE": 218, "CH": 0, "DE": 0, "ES": 1684, "GB": 0, "IT-NO": 0}, "powerExportBreakdown": {"BE": 0, "CH": 1899, "DE": 2034, "ES": 0, "GB": 2516, "IT-NO": 3044}, "fossilFreePercentage": 98, "renewablePercentage": 22, "powerConsumptionTotal": 40938, "powerProductionTotal": 50735, "powerImportTotal": 1903, "powerExportTotal": 9493, "isEstimated": false, "estimationMethod": null}, {"zone": "FR", "datetime": "2025-04-16T04:00:00.000Z", "updatedAt": "2025-04-16T15:42:57.967Z", "createdAt": "2025-04-13T04:41:40.454Z", "powerConsumptionBreakdown": {"nuclear": 34342, "geothermal": 0, "biomass": 825, "coal": 10, "wind": 3848, "solar": 101, "hydro": 5263, "gas": 546, "oil": 67, "unknown": 5, "hydro discharge": 19, "battery discharge": 0}, "powerProductionBreakdown": {"nuclear": 41337, "geothermal": null, "biomass": 956, "coal": 0, "wind": 3771, "solar": 123, "hydro": 5953, "gas": 403, "oil": 80, "unknown": null, "hydro discharge": -431, "battery discharge": -19}, "powerImportBreakdown": {"BE": 0, "CH": 0, "DE": 0, "ES": 1818, "GB": 0, "IT-NO": 0}, "powerExportBreakdown": {"BE": 120, "CH": 1095, "DE": 2401, "ES": 0, "GB": 2495, "IT-NO": 2852}, "fossilFreePercentage": 99, "renewablePercentage": 22, "powerConsumptionTotal": 45027, "powerProductionTotal": 52622, "powerImportTotal": 1818, "powerExportTotal": 8962, "isEstimated": false, "estimationMethod": null}, {"zone": "FR", "datetime": "2025-04-16T05:00:00.000Z", "updatedAt": "2025-04-16T15:42:32.606Z", "createdAt": "2025-04-13T05:42:32.621Z", "powerConsumptionBreakdown": {"nuclear": 36069, "geothermal": 0, "biomass": 841, "coal": 9, "wind": 3562, "solar": 341, "hydro": 5855, "gas": 697, "oil": 205, "unknown": 5, "hydro discharge": 1403, "battery discharge": 2}, "powerProductionBreakdown": {"nuclear": 42431, "geothermal": null, "biomass": 954, "coal": 0, "wind": 3382, "solar": 403, "hydro": 6484, "gas": 587, "oil": 245, "unknown": null, "hydro discharge": 1640, "battery discharge": -2}, "powerImportBreakdown": {"BE": 0, "CH": 0, "DE": 0, "ES": 1762, "GB": 0, "IT-NO": 0}, "powerExportBreakdown": {"BE": 703, "CH": 42, "DE": 2363, "ES": 0, "GB": 2977, "IT-NO": 2813}, "fossilFreePercentage": 98, "renewablePercentage": 25, "powerConsumptionTotal": 48988, "powerProductionTotal": 56126, "powerImportTotal": 1762, "powerExportTotal": 8898, "isEstimated": false, "estimationMethod": null}, {"zone": "FR", "datetime": "2025-04-16T06:00:00.000Z", "updatedAt": "2025-04-16T15:42:57.967Z", "createdAt": "2025-04-13T06:43:18.299Z", "powerConsumptionBreakdown": {"nuclear": 37061, "geothermal": 0, "biomass": 854, "coal": 9, "wind": 3449, "solar": 1252, "hydro": 6263, "gas": 782, "oil": 493, "unknown": 5, "hydro discharge": 2209, "battery discharge": 5}, "powerProductionBreakdown": {"nuclear": 42644, "geothermal": null, "biomass": 954, "coal": 0, "wind": 3310, "solar": 1310, "hydro": 6838, "gas": 697, "oil": 568, "unknown": null, "hydro discharge": 2535, "battery discharge": 5}, "powerImportBreakdown": {"BE": 0, "CH": 0, "DE": 0, "ES": 1628, "GB": 0, "IT-NO": 0}, "powerExportBreakdown": {"BE": 641, "CH": 15, "DE": 2047, "ES": 0, "GB": 2693, "IT-NO": 2711}, "fossilFreePercentage": 98, "renewablePercentage": 27, "powerConsumptionTotal": 52382, "powerProductionTotal": 58861, "powerImportTotal": 1628, "powerExportTotal": 8107, "isEstimated": false, "estimationMethod": null}, {"zone": "FR", "datetime": "2025-04-16T07:00:00.000Z", "updatedAt": "2025-04-16T15:42:57.967Z", "createdAt": "2025-04-13T07:44:31.532Z", "powerConsumptionBreakdown": {"nuclear": 37802, "geothermal": 0, "biomass": 855, "coal": 8, "wind": 3198, "solar": 3438, "hydro": 6148, "gas": 643, "oil": 226, "unknown": 10, "hydro discharge": 1582, "battery discharge": 0}, "powerProductionBreakdown": {"nuclear": 42712, "geothermal": null, "biomass": 946, "coal": 0, "wind": 3157, "solar": 3409, "hydro": 6644, "gas": 585, "oil": 256, "unknown": null, "hydro discharge": 1796, "battery discharge": -13}, "powerImportBreakdown": {"BE": 0, "CH": 247, "DE": 0, "ES": 1452, "GB": 0, "IT-NO": 0}, "powerExportBreakdown": {"BE": 650, "CH": 0, "DE": 1672, "ES": 0, "GB": 2488, "IT-NO": 2471}, "fossilFreePercentage": 98, "renewablePercentage": 28, "powerConsumptionTotal": 53910, "powerProductionTotal": 59505, "powerImportTotal": 1699, "powerExportTotal": 7281, "isEstimated": false, "estimationMethod": null}, {"zone": "FR", "datetime": "2025-04-16T08:00:00.000Z", "updatedAt": "2025-04-16T15:42:57.967Z", "createdAt": "2025-04-13T08:42:52.759Z", "powerConsumptionBreakdown": {"nuclear": 37222, "geothermal": 0, "biomass": 846, "coal": 10, "wind": 2949, "solar": 5909, "hydro": 5738, "gas": 601, "oil": 70, "unknown": 4, "hydro discharge": 488, "battery discharge": 0}, "powerProductionBreakdown": {"nuclear": 42829, "geothermal": null, "biomass": 950, "coal": 0, "wind": 2916, "solar": 6004, "hydro": 6438, "gas": 545, "oil": 80, "unknown": null, "hydro discharge": 562, "battery discharge": -19}, "powerImportBreakdown": {"BE": 0, "CH": 0, "DE": 0, "ES": 1837, "GB": 0, "IT-NO": 0}, "powerExportBreakdown": {"BE": 1016, "CH": 181, "DE": 1398, "ES": 0, "GB": 2757, "IT-NO": 2950}, "fossilFreePercentage": 99, "renewablePercentage": 30, "powerConsumptionTotal": 53838, "powerProductionTotal": 60322, "powerImportTotal": 1837, "powerExportTotal": 8302, "isEstimated": false, "estimationMethod": null}, {"zone": "FR", "datetime": "2025-04-16T09:00:00.000Z", "updatedAt": "2025-04-16T15:42:52.650Z", "createdAt": "2025-04-13T09:43:02.982Z", "powerConsumptionBreakdown": {"nuclear": 37021, "geothermal": 0, "biomass": 843, "coal": 8, "wind": 2640, "solar": 7532, "hydro": 5531, "gas": 547, "oil": 69, "unknown": 3, "hydro discharge": 171, "battery discharge": 3}, "powerProductionBreakdown": {"nuclear": 42921, "geothermal": null, "biomass": 960, "coal": 0, "wind": 2766, "solar": 8061, "hydro": 6301, "gas": 527, "oil": 80, "unknown": null, "hydro discharge": 199, "battery discharge": -3}, "powerImportBreakdown": {"BE": 0, "CH": 0, "DE": 0, "ES": 1376, "GB": 0, "IT-NO": 0}, "powerExportBreakdown": {"BE": 850, "CH": 566, "DE": 1468, "ES": 0, "GB": 2989, "IT-NO": 2945}, "fossilFreePercentage": 99, "renewablePercentage": 31, "powerConsumptionTotal": 54368, "powerProductionTotal": 61813, "powerImportTotal": 1376, "powerExportTotal": 8818, "isEstimated": false, "estimationMethod": null}, {"zone": "FR", "datetime": "2025-04-16T10:00:00.000Z", "updatedAt": "2025-04-16T15:42:32.606Z", "createdAt": "2025-04-13T10:42:43.284Z", "powerConsumptionBreakdown": {"nuclear": 37117, "geothermal": 0, "biomass": 846, "coal": 7, "wind": 2753, "solar": 8458, "hydro": 5437, "gas": 541, "oil": 70, "unknown": 3, "hydro discharge": 0, "battery discharge": 1}, "powerProductionBreakdown": {"nuclear": 42851, "geothermal": null, "biomass": 959, "coal": 0, "wind": 2918, "solar": 9140, "hydro": 6179, "gas": 530, "oil": 81, "unknown": null, "hydro discharge": -166, "battery discharge": 1}, "powerImportBreakdown": {"BE": 0, "CH": 0, "DE": 0, "ES": 1260, "GB": 0, "IT-NO": 0}, "powerExportBreakdown": {"BE": 789, "CH": 481, "DE": 1439, "ES": 0, "GB": 2992, "IT-NO": 2818}, "fossilFreePercentage": 99, "renewablePercentage": 32, "powerConsumptionTotal": 55234, "powerProductionTotal": 62659, "powerImportTotal": 1260, "powerExportTotal": 8519, "isEstimated": false, "estimationMethod": null}, {"zone": "FR", "datetime": "2025-04-16T11:00:00.000Z", "updatedAt": "2025-04-16T15:42:32.606Z", "createdAt": "2025-04-13T11:44:31.248Z", "powerConsumptionBreakdown": {"nuclear": 35661, "geothermal": 0, "biomass": 820, "coal": 8, "wind": 2735, "solar": 8243, "hydro": 5122, "gas": 557, "oil": 67, "unknown": 4, "hydro discharge": 0, "battery discharge": 0}, "powerProductionBreakdown": {"nuclear": 42572, "geothermal": null, "biomass": 959, "coal": 0, "wind": 2933, "solar": 9111, "hydro": 5994, "gas": 551, "oil": 80, "unknown": null, "hydro discharge": -952, "battery discharge": -8}, "powerImportBreakdown": {"BE": 0, "CH": 0, "DE": 0, "ES": 1515, "GB": 0, "IT-NO": 0}, "powerExportBreakdown": {"BE": 1207, "CH": 796, "DE": 1583, "ES": 0, "GB": 2992, "IT-NO": 2961}, "fossilFreePercentage": 99, "renewablePercentage": 32, "powerConsumptionTotal": 53216, "powerProductionTotal": 62199, "powerImportTotal": 1515, "powerExportTotal": 9539, "isEstimated": false, "estimationMethod": null}, {"zone": "FR", "datetime": "2025-04-16T12:00:00.000Z", "updatedAt": "2025-04-16T14:49:09.297Z", "createdAt": "2025-04-13T12:45:05.470Z", "powerConsumptionBreakdown": {"nuclear": 34308, "geothermal": 0, "biomass": 798, "coal": 9, "wind": 2555, "solar": 8252, "hydro": 4996, "gas": 546, "oil": 66, "unknown": 3, "hydro discharge": 0, "battery discharge": 0}, "powerProductionBreakdown": {"nuclear": 41749, "geothermal": null, "biomass": 949, "coal": 0, "wind": 2715, "solar": 9317, "hydro": 5945, "gas": 538, "oil": 80, "unknown": null, "hydro discharge": -917, "battery discharge": -7}, "powerImportBreakdown": {"BE": 0, "CH": 0, "DE": 0, "ES": 1618, "GB": 0, "IT-NO": 0}, "powerExportBreakdown": {"BE": 1290, "CH": 1134, "DE": 1890, "ES": 0, "GB": 2992, "IT-NO": 3149}, "fossilFreePercentage": 99, "renewablePercentage": 32, "powerConsumptionTotal": 51534, "powerProductionTotal": 61294, "powerImportTotal": 1618, "powerExportTotal": 10454, "isEstimated": false, "estimationMethod": null}, {"zone": "FR", "datetime": "2025-04-16T13:00:00.000Z", "updatedAt": "2025-04-16T15:42:32.606Z", "createdAt": "2025-04-13T13:45:55.615Z", "powerConsumptionBreakdown": {"nuclear": 33430, "geothermal": 0, "biomass": 793, "coal": 9, "wind": 2446, "solar": 7567, "hydro": 4766, "gas": 531, "oil": 66, "unknown": 3, "hydro discharge": 0, "battery discharge": 0}, "powerProductionBreakdown": {"nuclear": 40926, "geothermal": null, "biomass": 949, "coal": 0, "wind": 2569, "solar": 8597, "hydro": 5701, "gas": 521, "oil": 81, "unknown": null, "hydro discharge": -719, "battery discharge": -15}, "powerImportBreakdown": {"BE": 0, "CH": 0, "DE": 0, "ES": 1591, "GB": 0, "IT-NO": 0}, "powerExportBreakdown": {"BE": 1217, "CH": 1361, "DE": 1827, "ES": 0, "GB": 2992, "IT-NO": 3192}, "fossilFreePercentage": 99, "renewablePercentage": 31, "powerConsumptionTotal": 49611, "powerProductionTotal": 59342, "powerImportTotal": 1591, "powerExportTotal": 10589, "isEstimated": false, "estimationMethod": null}, {"zone": "FR", "datetime": "2025-04-16T14:00:00.000Z", "updatedAt": "2025-04-16T15:42:52.650Z", "createdAt": "2025-04-13T14:41:34.809Z", "powerConsumptionBreakdown": {"nuclear": 32861, "geothermal": 0, "biomass": 789, "coal": 7, "wind": 2510, "solar": 6784, "hydro": 4853, "gas": 513, "oil": 66, "unknown": 2, "hydro discharge": 0, "battery discharge": 2}, "powerProductionBreakdown": {"nuclear": 40401, "geothermal": null, "biomass": 954, "coal": 0, "wind": 2746, "solar": 7879, "hydro": 5851, "gas": 532, "oil": 81, "unknown": null, "hydro discharge": -745, "battery discharge": 0}, "powerImportBreakdown": {"BE": 0, "CH": 0, "DE": 0, "ES": 1194, "GB": 0, "IT-NO": 0}, "powerExportBreakdown": {"BE": 1290, "CH": 1056, "DE": 1827, "ES": 0, "GB": 2992, "IT-NO": 3342}, "fossilFreePercentage": 99, "renewablePercentage": 31, "powerConsumptionTotal": 48387, "powerProductionTotal": 58445, "powerImportTotal": 1194, "powerExportTotal": 10507, "isEstimated": false, "estimationMethod": null}, {"zone": "FR", "datetime": "2025-04-16T15:00:00.000Z", "updatedAt": "2025-04-16T15:42:52.650Z", "createdAt": "2025-04-13T15:41:29.367Z", "powerConsumptionBreakdown": {"nuclear": 32594, "geothermal": 0, "biomass": 783, "coal": 7, "wind": 2497, "solar": 6743, "hydro": 4816, "gas": 512, "oil": 65, "unknown": 2, "hydro discharge": 0, "battery discharge": 0}, "powerProductionBreakdown": {"nuclear": 40401, "geothermal": null, "biomass": 954, "coal": 0, "wind": 2746, "solar": 7879, "hydro": 5851, "gas": 532, "oil": 81, "unknown": null, "hydro discharge": -745, "battery discharge": 0}, "powerImportBreakdown": {"BE": 0, "CH": 0, "DE": 0, "ES": 1233, "GB": 0, "IT-NO": 0}, "powerExportBreakdown": {"BE": 1290, "CH": 1056, "DE": 2243, "ES": 0, "GB": 2992, "IT-NO": 3331}, "fossilFreePercentage": 99, "renewablePercentage": 31, "powerConsumptionTotal": 48020, "powerProductionTotal": 58445, "powerImportTotal": 1233, "powerExportTotal": 10911, "isEstimated": true, "estimationMethod": "TIME_SLICER_AVERAGE"}, {"zone": "FR", "datetime": "2025-04-16T16:00:00.000Z", "updatedAt": "2025-04-16T15:42:52.650Z", "createdAt": "2025-04-13T16:46:30.160Z", "powerConsumptionBreakdown": {"nuclear": 34482, "geothermal": 0, "biomass": 805, "coal": 10, "wind": 3131, "solar": 4495, "hydro": 5576, "gas": 590, "oil": 66, "unknown": 4, "hydro discharge": 442, "battery discharge": 0}, "powerProductionBreakdown": {"nuclear": 42147, "geothermal": null, "biomass": 956, "coal": 0, "wind": 3227, "solar": 4826, "hydro": 6569, "gas": 543, "oil": 81, "unknown": null, "hydro discharge": 542, "battery discharge": -1}, "powerImportBreakdown": {"BE": 0, "CH": 0, "DE": 0, "ES": 1972, "GB": 0, "IT-NO": 0}, "powerExportBreakdown": {"BE": 1443, "CH": 770, "DE": 2620, "ES": 0, "GB": 3035, "IT-NO": 3394}, "fossilFreePercentage": 99, "renewablePercentage": 29, "powerConsumptionTotal": 49601, "powerProductionTotal": 58892, "powerImportTotal": 1972, "powerExportTotal": 11261, "isEstimated": true, "estimationMethod": "TIME_SLICER_AVERAGE"}]}