{"zone": "FR", "history": [{"zone": "FR", "datetime": "2025-05-30T17:00:00.000Z", "updatedAt": "2025-05-30T19:43:46.865Z", "createdAt": "2025-05-27T17:45:11.474Z", "powerConsumptionBreakdown": {"nuclear": 30027, "geothermal": 0, "biomass": 802, "coal": 9, "wind": 1097, "solar": 4302, "hydro": 5743, "gas": 603, "oil": 67, "unknown": 4, "hydro discharge": 1662, "battery discharge": 0}, "powerProductionBreakdown": {"nuclear": 37707, "geothermal": null, "biomass": 984, "coal": 0, "wind": 957, "solar": 4760, "hydro": 7081, "gas": 408, "oil": 81, "unknown": null, "hydro discharge": 2081, "battery discharge": -1}, "powerImportBreakdown": {"BE": 0, "CH": 0, "DE": 0, "ES": 2133, "GB": 0, "IT-NO": 0}, "powerExportBreakdown": {"BE": 2092, "CH": 600, "DE": 2987, "ES": 0, "GB": 2353, "IT-NO": 3842}, "fossilFreePercentage": 98, "renewablePercentage": 31, "powerConsumptionTotal": 44315, "powerProductionTotal": 54057, "powerImportTotal": 2133, "powerExportTotal": 11873, "isEstimated": false, "estimationMethod": null}, {"zone": "FR", "datetime": "2025-05-30T18:00:00.000Z", "updatedAt": "2025-05-30T20:44:35.556Z", "createdAt": "2025-05-27T18:42:50.208Z", "powerConsumptionBreakdown": {"nuclear": 30238, "geothermal": 0, "biomass": 783, "coal": 6, "wind": 1008, "solar": 1546, "hydro": 6478, "gas": 522, "oil": 65, "unknown": 2, "hydro discharge": 2883, "battery discharge": 1}, "powerProductionBreakdown": {"nuclear": 38355, "geothermal": null, "biomass": 979, "coal": 0, "wind": 1009, "solar": 1722, "hydro": 8121, "gas": 393, "oil": 81, "unknown": null, "hydro discharge": 3636, "battery discharge": 1}, "powerImportBreakdown": {"BE": 0, "CH": 0, "DE": 0, "ES": 1265, "GB": 0, "IT-NO": 0}, "powerExportBreakdown": {"BE": 2199, "CH": 172, "DE": 3320, "ES": 0, "GB": 2353, "IT-NO": 3985}, "fossilFreePercentage": 99, "renewablePercentage": 29, "powerConsumptionTotal": 43532, "powerProductionTotal": 54297, "powerImportTotal": 1265, "powerExportTotal": 12029, "isEstimated": false, "estimationMethod": null}, {"zone": "FR", "datetime": "2025-05-30T19:00:00.000Z", "updatedAt": "2025-05-31T12:43:13.956Z", "createdAt": "2025-05-27T19:45:50.375Z", "powerConsumptionBreakdown": {"nuclear": 30154, "geothermal": 0, "biomass": 763, "coal": 0, "wind": 821, "solar": 362, "hydro": 6911, "gas": 323, "oil": 63, "unknown": 3, "hydro discharge": 2983, "battery discharge": 1}, "powerProductionBreakdown": {"nuclear": 38703, "geothermal": null, "biomass": 979, "coal": 0, "wind": 1036, "solar": 456, "hydro": 8794, "gas": 390, "oil": 81, "unknown": null, "hydro discharge": 3826, "battery discharge": 2}, "powerImportBreakdown": {"BE": 0, "CH": 107, "DE": 0, "ES": 0, "GB": 0, "IT-NO": 0}, "powerExportBreakdown": {"BE": 2108, "CH": 0, "DE": 3232, "ES": 437, "GB": 2351, "IT-NO": 3861}, "fossilFreePercentage": 99, "renewablePercentage": 28, "powerConsumptionTotal": 42385, "powerProductionTotal": 54266, "powerImportTotal": 107, "powerExportTotal": 11987, "isEstimated": false, "estimationMethod": null}, {"zone": "FR", "datetime": "2025-05-30T20:00:00.000Z", "updatedAt": "2025-05-31T12:43:13.956Z", "createdAt": "2025-05-27T20:44:20.613Z", "powerConsumptionBreakdown": {"nuclear": 31045, "geothermal": 0, "biomass": 764, "coal": 0, "wind": 826, "solar": 60, "hydro": 7467, "gas": 404, "oil": 66, "unknown": 20, "hydro discharge": 2997, "battery discharge": 0}, "powerProductionBreakdown": {"nuclear": 38615, "geothermal": null, "biomass": 955, "coal": 0, "wind": 1025, "solar": 65, "hydro": 8918, "gas": 496, "oil": 82, "unknown": null, "hydro discharge": 3747, "battery discharge": -5}, "powerImportBreakdown": {"BE": 0, "CH": 666, "DE": 0, "ES": 0, "GB": 0, "IT-NO": 0}, "powerExportBreakdown": {"BE": 1981, "CH": 0, "DE": 2893, "ES": 547, "GB": 2115, "IT-NO": 3378}, "fossilFreePercentage": 99, "renewablePercentage": 28, "powerConsumptionTotal": 43649, "powerProductionTotal": 53902, "powerImportTotal": 666, "powerExportTotal": 10914, "isEstimated": false, "estimationMethod": null}, {"zone": "FR", "datetime": "2025-05-30T21:00:00.000Z", "updatedAt": "2025-05-31T12:43:33.617Z", "createdAt": "2025-05-27T21:44:48.076Z", "powerConsumptionBreakdown": {"nuclear": 30877, "geothermal": 0, "biomass": 772, "coal": 2, "wind": 909, "solar": 7, "hydro": 7217, "gas": 480, "oil": 66, "unknown": 7, "hydro discharge": 2948, "battery discharge": 0}, "powerProductionBreakdown": {"nuclear": 38703, "geothermal": null, "biomass": 964, "coal": 0, "wind": 1086, "solar": 0, "hydro": 8869, "gas": 484, "oil": 83, "unknown": null, "hydro discharge": 3678, "battery discharge": -2}, "powerImportBreakdown": {"BE": 0, "CH": 192, "DE": 0, "ES": 323, "GB": 0, "IT-NO": 0}, "powerExportBreakdown": {"BE": 2108, "CH": 0, "DE": 2954, "ES": 0, "GB": 2314, "IT-NO": 3716}, "fossilFreePercentage": 99, "renewablePercentage": 27, "powerConsumptionTotal": 43285, "powerProductionTotal": 53865, "powerImportTotal": 515, "powerExportTotal": 11092, "isEstimated": false, "estimationMethod": null}, {"zone": "FR", "datetime": "2025-05-30T22:00:00.000Z", "updatedAt": "2025-05-31T12:43:33.617Z", "createdAt": "2025-05-27T22:43:17.044Z", "powerConsumptionBreakdown": {"nuclear": 30107, "geothermal": 0, "biomass": 757, "coal": 0, "wind": 909, "solar": 0, "hydro": 6354, "gas": 304, "oil": 64, "unknown": 3, "hydro discharge": 2502, "battery discharge": 5}, "powerProductionBreakdown": {"nuclear": 38600, "geothermal": null, "biomass": 971, "coal": 0, "wind": 1166, "solar": 0, "hydro": 8100, "gas": 391, "oil": 82, "unknown": null, "hydro discharge": 3211, "battery discharge": 3}, "powerImportBreakdown": {"BE": 0, "CH": 93, "DE": 0, "ES": 0, "GB": 0, "IT-NO": 0}, "powerExportBreakdown": {"BE": 2719, "CH": 0, "DE": 2666, "ES": 798, "GB": 2110, "IT-NO": 3319}, "fossilFreePercentage": 99, "renewablePercentage": 26, "powerConsumptionTotal": 41005, "powerProductionTotal": 52524, "powerImportTotal": 93, "powerExportTotal": 11612, "isEstimated": false, "estimationMethod": null}, {"zone": "FR", "datetime": "2025-05-30T23:00:00.000Z", "updatedAt": "2025-05-31T12:43:13.956Z", "createdAt": "2025-05-27T23:43:08.005Z", "powerConsumptionBreakdown": {"nuclear": 28386, "geothermal": 0, "biomass": 719, "coal": 0, "wind": 870, "solar": 0, "hydro": 5458, "gas": 275, "oil": 60, "unknown": 3, "hydro discharge": 2241, "battery discharge": 0}, "powerProductionBreakdown": {"nuclear": 38546, "geothermal": null, "biomass": 978, "coal": 0, "wind": 1183, "solar": 0, "hydro": 7346, "gas": 374, "oil": 82, "unknown": null, "hydro discharge": 3047, "battery discharge": -7}, "powerImportBreakdown": {"BE": 0, "CH": 121, "DE": 0, "ES": 0, "GB": 0, "IT-NO": 0}, "powerExportBreakdown": {"BE": 2853, "CH": 0, "DE": 2672, "ES": 2627, "GB": 2350, "IT-NO": 3154}, "fossilFreePercentage": 99, "renewablePercentage": 24, "powerConsumptionTotal": 38013, "powerProductionTotal": 51555, "powerImportTotal": 121, "powerExportTotal": 13656, "isEstimated": false, "estimationMethod": null}, {"zone": "FR", "datetime": "2025-05-31T00:00:00.000Z", "updatedAt": "2025-05-31T06:42:38.565Z", "createdAt": "2025-05-28T00:41:42.782Z", "powerConsumptionBreakdown": {"nuclear": 27549, "geothermal": 0, "biomass": 700, "coal": 0, "wind": 852, "solar": 0, "hydro": 4848, "gas": 268, "oil": 58, "unknown": 0, "hydro discharge": 1836, "battery discharge": 0}, "powerProductionBreakdown": {"nuclear": 38508, "geothermal": null, "biomass": 979, "coal": 0, "wind": 1191, "solar": 0, "hydro": 6777, "gas": 374, "oil": 81, "unknown": null, "hydro discharge": 2568, "battery discharge": -15}, "powerImportBreakdown": {"BE": 0, "CH": 0, "DE": 0, "ES": 0, "GB": 0, "IT-NO": 0}, "powerExportBreakdown": {"BE": 2889, "CH": 44, "DE": 3003, "ES": 2914, "GB": 2356, "IT-NO": 3148}, "fossilFreePercentage": 99, "renewablePercentage": 23, "powerConsumptionTotal": 36110, "powerProductionTotal": 50478, "powerImportTotal": 0, "powerExportTotal": 14353, "isEstimated": false, "estimationMethod": null}, {"zone": "FR", "datetime": "2025-05-31T01:00:00.000Z", "updatedAt": "2025-05-31T06:42:53.188Z", "createdAt": "2025-05-28T01:44:41.148Z", "powerConsumptionBreakdown": {"nuclear": 26716, "geothermal": 0, "biomass": 686, "coal": 0, "wind": 839, "solar": 0, "hydro": 4315, "gas": 261, "oil": 56, "unknown": 0, "hydro discharge": 962, "battery discharge": 0}, "powerProductionBreakdown": {"nuclear": 38356, "geothermal": null, "biomass": 985, "coal": 0, "wind": 1205, "solar": 0, "hydro": 6195, "gas": 374, "oil": 80, "unknown": null, "hydro discharge": 1384, "battery discharge": -19}, "powerImportBreakdown": {"BE": 0, "CH": 0, "DE": 0, "ES": 0, "GB": 0, "IT-NO": 0}, "powerExportBreakdown": {"BE": 2916, "CH": 210, "DE": 3304, "ES": 2973, "GB": 2358, "IT-NO": 2963}, "fossilFreePercentage": 99, "renewablePercentage": 20, "powerConsumptionTotal": 33835, "powerProductionTotal": 48578, "powerImportTotal": 0, "powerExportTotal": 14724, "isEstimated": false, "estimationMethod": null}, {"zone": "FR", "datetime": "2025-05-31T02:00:00.000Z", "updatedAt": "2025-05-31T06:42:58.266Z", "createdAt": "2025-05-28T02:43:32.338Z", "powerConsumptionBreakdown": {"nuclear": 26260, "geothermal": 0, "biomass": 674, "coal": 0, "wind": 951, "solar": 0, "hydro": 4069, "gas": 255, "oil": 56, "unknown": 0, "hydro discharge": 263, "battery discharge": 0}, "powerProductionBreakdown": {"nuclear": 38264, "geothermal": null, "biomass": 982, "coal": 0, "wind": 1385, "solar": 0, "hydro": 5930, "gas": 372, "oil": 82, "unknown": null, "hydro discharge": 384, "battery discharge": -24}, "powerImportBreakdown": {"BE": 0, "CH": 0, "DE": 0, "ES": 0, "GB": 0, "IT-NO": 0}, "powerExportBreakdown": {"BE": 2937, "CH": 308, "DE": 3552, "ES": 2763, "GB": 2356, "IT-NO": 2930}, "fossilFreePercentage": 99, "renewablePercentage": 18, "powerConsumptionTotal": 32528, "powerProductionTotal": 47398, "powerImportTotal": 0, "powerExportTotal": 14845, "isEstimated": false, "estimationMethod": null}, {"zone": "FR", "datetime": "2025-05-31T03:00:00.000Z", "updatedAt": "2025-05-31T06:42:58.266Z", "createdAt": "2025-05-28T03:46:00.923Z", "powerConsumptionBreakdown": {"nuclear": 26232, "geothermal": 0, "biomass": 672, "coal": 0, "wind": 968, "solar": 0, "hydro": 4006, "gas": 254, "oil": 57, "unknown": 0, "hydro discharge": 89, "battery discharge": 0}, "powerProductionBreakdown": {"nuclear": 38289, "geothermal": null, "biomass": 982, "coal": 0, "wind": 1413, "solar": 0, "hydro": 5847, "gas": 370, "oil": 83, "unknown": null, "hydro discharge": 130, "battery discharge": -21}, "powerImportBreakdown": {"BE": 0, "CH": 0, "DE": 0, "ES": 0, "GB": 0, "IT-NO": 0}, "powerExportBreakdown": {"BE": 3040, "CH": 348, "DE": 3421, "ES": 2704, "GB": 2354, "IT-NO": 2948}, "fossilFreePercentage": 99, "renewablePercentage": 18, "powerConsumptionTotal": 32277, "powerProductionTotal": 47113, "powerImportTotal": 0, "powerExportTotal": 14815, "isEstimated": false, "estimationMethod": null}, {"zone": "FR", "datetime": "2025-05-31T04:00:00.000Z", "updatedAt": "2025-05-31T06:42:38.565Z", "createdAt": "2025-05-28T04:43:13.664Z", "powerConsumptionBreakdown": {"nuclear": 26329, "geothermal": 0, "biomass": 671, "coal": 0, "wind": 870, "solar": 287, "hydro": 4064, "gas": 260, "oil": 56, "unknown": 0, "hydro discharge": 117, "battery discharge": 0}, "powerProductionBreakdown": {"nuclear": 38137, "geothermal": null, "biomass": 973, "coal": 0, "wind": 1261, "solar": 416, "hydro": 5887, "gas": 376, "oil": 82, "unknown": null, "hydro discharge": 170, "battery discharge": -11}, "powerImportBreakdown": {"BE": 0, "CH": 0, "DE": 0, "ES": 0, "GB": 0, "IT-NO": 0}, "powerExportBreakdown": {"BE": 3233, "CH": 361, "DE": 3355, "ES": 2700, "GB": 2354, "IT-NO": 2633}, "fossilFreePercentage": 99, "renewablePercentage": 18, "powerConsumptionTotal": 32654, "powerProductionTotal": 47301, "powerImportTotal": 0, "powerExportTotal": 14635, "isEstimated": false, "estimationMethod": null}, {"zone": "FR", "datetime": "2025-05-31T05:00:00.000Z", "updatedAt": "2025-05-31T07:44:43.841Z", "createdAt": "2025-05-28T05:44:50.184Z", "powerConsumptionBreakdown": {"nuclear": 26571, "geothermal": 0, "biomass": 685, "coal": 0, "wind": 844, "solar": 1113, "hydro": 4167, "gas": 268, "oil": 58, "unknown": 0, "hydro discharge": 232, "battery discharge": 0}, "powerProductionBreakdown": {"nuclear": 37394, "geothermal": null, "biomass": 964, "coal": 0, "wind": 1188, "solar": 1569, "hydro": 5864, "gas": 377, "oil": 82, "unknown": null, "hydro discharge": 326, "battery discharge": -18}, "powerImportBreakdown": {"BE": 0, "CH": 0, "DE": 0, "ES": 0, "GB": 0, "IT-NO": 0}, "powerExportBreakdown": {"BE": 3167, "CH": 550, "DE": 2965, "ES": 2695, "GB": 2352, "IT-NO": 2078}, "fossilFreePercentage": 99, "renewablePercentage": 21, "powerConsumptionTotal": 33938, "powerProductionTotal": 47763, "powerImportTotal": 0, "powerExportTotal": 13807, "isEstimated": false, "estimationMethod": null}, {"zone": "FR", "datetime": "2025-05-31T06:00:00.000Z", "updatedAt": "2025-05-31T08:42:17.455Z", "createdAt": "2025-05-28T06:43:48.028Z", "powerConsumptionBreakdown": {"nuclear": 26683, "geothermal": 0, "biomass": 707, "coal": 0, "wind": 780, "solar": 3110, "hydro": 4413, "gas": 278, "oil": 59, "unknown": 0, "hydro discharge": 97, "battery discharge": 8}, "powerProductionBreakdown": {"nuclear": 36463, "geothermal": null, "biomass": 966, "coal": 0, "wind": 1066, "solar": 4257, "hydro": 6030, "gas": 379, "oil": 81, "unknown": null, "hydro discharge": -97, "battery discharge": 11}, "powerImportBreakdown": {"BE": 0, "CH": 0, "DE": 0, "ES": 0, "GB": 0, "IT-NO": 0}, "powerExportBreakdown": {"BE": 3191, "CH": 997, "DE": 2621, "ES": 2508, "GB": 2352, "IT-NO": 1353}, "fossilFreePercentage": 99, "renewablePercentage": 25, "powerConsumptionTotal": 36135, "powerProductionTotal": 49254, "powerImportTotal": 0, "powerExportTotal": 13021, "isEstimated": false, "estimationMethod": null}, {"zone": "FR", "datetime": "2025-05-31T07:00:00.000Z", "updatedAt": "2025-05-31T09:44:27.014Z", "createdAt": "2025-05-28T07:44:23.103Z", "powerConsumptionBreakdown": {"nuclear": 26431, "geothermal": 0, "biomass": 769, "coal": 1, "wind": 755, "solar": 6073, "hydro": 4486, "gas": 319, "oil": 64, "unknown": 0, "hydro discharge": 0, "battery discharge": 16}, "powerProductionBreakdown": {"nuclear": 33246, "geothermal": null, "biomass": 965, "coal": 0, "wind": 944, "solar": 7545, "hydro": 5635, "gas": 373, "oil": 81, "unknown": null, "hydro discharge": -1152, "battery discharge": 20}, "powerImportBreakdown": {"BE": 0, "CH": 0, "DE": 0, "ES": 0, "GB": 0, "IT-NO": 0}, "powerExportBreakdown": {"BE": 2321, "CH": 792, "DE": 2022, "ES": 311, "GB": 2350, "IT-NO": 945}, "fossilFreePercentage": 99, "renewablePercentage": 31, "powerConsumptionTotal": 38915, "powerProductionTotal": 48807, "powerImportTotal": 0, "powerExportTotal": 8740, "isEstimated": false, "estimationMethod": null}, {"zone": "FR", "datetime": "2025-05-31T08:00:00.000Z", "updatedAt": "2025-05-31T15:43:24.565Z", "createdAt": "2025-05-28T08:44:49.774Z", "powerConsumptionBreakdown": {"nuclear": 27325, "geothermal": 0, "biomass": 874, "coal": 17, "wind": 719, "solar": 7659, "hydro": 4800, "gas": 370, "oil": 72, "unknown": 14, "hydro discharge": 0, "battery discharge": 4}, "powerProductionBreakdown": {"nuclear": 30843, "geothermal": null, "biomass": 964, "coal": 0, "wind": 803, "solar": 8190, "hydro": 5185, "gas": 379, "oil": 80, "unknown": null, "hydro discharge": -1637, "battery discharge": 1}, "powerImportBreakdown": {"BE": 0, "CH": 567, "DE": 49, "ES": 91, "GB": 0, "IT-NO": 0}, "powerExportBreakdown": {"BE": 998, "CH": 0, "DE": 0, "ES": 0, "GB": 2340, "IT-NO": 322}, "fossilFreePercentage": 99, "renewablePercentage": 34, "powerConsumptionTotal": 41854, "powerProductionTotal": 46444, "powerImportTotal": 707, "powerExportTotal": 3660, "isEstimated": false, "estimationMethod": null}, {"zone": "FR", "datetime": "2025-05-31T09:00:00.000Z", "updatedAt": "2025-05-31T15:43:24.565Z", "createdAt": "2025-05-28T09:45:14.783Z", "powerConsumptionBreakdown": {"nuclear": 26223, "geothermal": 0, "biomass": 880, "coal": 22, "wind": 726, "solar": 8848, "hydro": 4544, "gas": 353, "oil": 72, "unknown": 15, "hydro discharge": 0, "battery discharge": 0}, "powerProductionBreakdown": {"nuclear": 29840, "geothermal": null, "biomass": 968, "coal": 0, "wind": 815, "solar": 9537, "hydro": 4927, "gas": 376, "oil": 81, "unknown": null, "hydro discharge": -2155, "battery discharge": -11}, "powerImportBreakdown": {"BE": 0, "CH": 618, "DE": 403, "ES": 0, "GB": 0, "IT-NO": 0}, "powerExportBreakdown": {"BE": 1151, "CH": 0, "DE": 0, "ES": 522, "GB": 1675, "IT-NO": 366}, "fossilFreePercentage": 99, "renewablePercentage": 36, "powerConsumptionTotal": 41684, "powerProductionTotal": 46543, "powerImportTotal": 1021, "powerExportTotal": 3714, "isEstimated": false, "estimationMethod": null}, {"zone": "FR", "datetime": "2025-05-31T10:00:00.000Z", "updatedAt": "2025-05-31T15:43:49.268Z", "createdAt": "2025-05-28T10:41:02.103Z", "powerConsumptionBreakdown": {"nuclear": 25940, "geothermal": 6, "biomass": 985, "coal": 82, "wind": 855, "solar": 11145, "hydro": 4805, "gas": 404, "oil": 79, "unknown": 45, "hydro discharge": 0, "battery discharge": 0}, "powerProductionBreakdown": {"nuclear": 28828, "geothermal": null, "biomass": 962, "coal": 0, "wind": 895, "solar": 10700, "hydro": 4686, "gas": 377, "oil": 81, "unknown": null, "hydro discharge": -1968, "battery discharge": -3}, "powerImportBreakdown": {"BE": 0, "CH": 1424, "DE": 1550, "ES": 0, "GB": 0, "IT-NO": 268}, "powerExportBreakdown": {"BE": 231, "CH": 0, "DE": 0, "ES": 1737, "GB": 1486, "IT-NO": 0}, "fossilFreePercentage": 99, "renewablePercentage": 40, "powerConsumptionTotal": 44345, "powerProductionTotal": 46529, "powerImportTotal": 3242, "powerExportTotal": 3454, "isEstimated": false, "estimationMethod": null}, {"zone": "FR", "datetime": "2025-05-31T11:00:00.000Z", "updatedAt": "2025-05-31T15:43:49.268Z", "createdAt": "2025-05-28T11:48:15.260Z", "powerConsumptionBreakdown": {"nuclear": 24153, "geothermal": 7, "biomass": 990, "coal": 92, "wind": 997, "solar": 11559, "hydro": 4590, "gas": 431, "oil": 77, "unknown": 63, "hydro discharge": 0, "battery discharge": 0}, "powerProductionBreakdown": {"nuclear": 27527, "geothermal": null, "biomass": 965, "coal": 0, "wind": 1063, "solar": 10937, "hydro": 4493, "gas": 381, "oil": 80, "unknown": null, "hydro discharge": -2086, "battery discharge": -2}, "powerImportBreakdown": {"BE": 500, "CH": 1625, "DE": 1840, "ES": 0, "GB": 0, "IT-NO": 353}, "powerExportBreakdown": {"BE": 0, "CH": 0, "DE": 0, "ES": 2787, "GB": 1926, "IT-NO": 0}, "fossilFreePercentage": 99, "renewablePercentage": 42, "powerConsumptionTotal": 42960, "powerProductionTotal": 45445, "powerImportTotal": 4317, "powerExportTotal": 4713, "isEstimated": false, "estimationMethod": null}, {"zone": "FR", "datetime": "2025-05-31T12:00:00.000Z", "updatedAt": "2025-05-31T15:43:24.565Z", "createdAt": "2025-05-28T12:42:53.142Z", "powerConsumptionBreakdown": {"nuclear": 24046, "geothermal": 1, "biomass": 902, "coal": 33, "wind": 960, "solar": 10044, "hydro": 4391, "gas": 358, "oil": 72, "unknown": 25, "hydro discharge": 0, "battery discharge": 0}, "powerProductionBreakdown": {"nuclear": 27249, "geothermal": null, "biomass": 972, "coal": 0, "wind": 1066, "solar": 10622, "hydro": 4538, "gas": 379, "oil": 79, "unknown": null, "hydro discharge": -2362, "battery discharge": -4}, "powerImportBreakdown": {"BE": 0, "CH": 1036, "DE": 633, "ES": 0, "GB": 0, "IT-NO": 11}, "powerExportBreakdown": {"BE": 57, "CH": 0, "DE": 0, "ES": 2964, "GB": 368, "IT-NO": 0}, "fossilFreePercentage": 99, "renewablePercentage": 40, "powerConsumptionTotal": 40831, "powerProductionTotal": 44906, "powerImportTotal": 1680, "powerExportTotal": 3389, "isEstimated": false, "estimationMethod": null}, {"zone": "FR", "datetime": "2025-05-31T13:00:00.000Z", "updatedAt": "2025-05-31T15:43:24.565Z", "createdAt": "2025-05-28T13:46:30.419Z", "powerConsumptionBreakdown": {"nuclear": 23482, "geothermal": 0, "biomass": 837, "coal": 2, "wind": 1096, "solar": 9068, "hydro": 4135, "gas": 323, "oil": 68, "unknown": 5, "hydro discharge": 0, "battery discharge": 0}, "powerProductionBreakdown": {"nuclear": 27257, "geothermal": null, "biomass": 970, "coal": 0, "wind": 1273, "solar": 10450, "hydro": 4701, "gas": 374, "oil": 79, "unknown": null, "hydro discharge": -2304, "battery discharge": -3}, "powerImportBreakdown": {"BE": 0, "CH": 238, "DE": 0, "ES": 0, "GB": 0, "IT-NO": 0}, "powerExportBreakdown": {"BE": 630, "CH": 0, "DE": 669, "ES": 1717, "GB": 473, "IT-NO": 528}, "fossilFreePercentage": 99, "renewablePercentage": 39, "powerConsumptionTotal": 39016, "powerProductionTotal": 45103, "powerImportTotal": 238, "powerExportTotal": 4017, "isEstimated": false, "estimationMethod": null}, {"zone": "FR", "datetime": "2025-05-31T14:00:00.000Z", "updatedAt": "2025-05-31T15:43:49.268Z", "createdAt": "2025-05-28T14:45:39.261Z", "powerConsumptionBreakdown": {"nuclear": 24128, "geothermal": 0, "biomass": 845, "coal": 6, "wind": 1383, "solar": 8425, "hydro": 4394, "gas": 441, "oil": 69, "unknown": 2, "hydro discharge": 0, "battery discharge": 0}, "powerProductionBreakdown": {"nuclear": 28136, "geothermal": null, "biomass": 973, "coal": 0, "wind": 1546, "solar": 9252, "hydro": 5103, "gas": 373, "oil": 79, "unknown": null, "hydro discharge": -1652, "battery discharge": -3}, "powerImportBreakdown": {"BE": 0, "CH": 0, "DE": 0, "ES": 1178, "GB": 0, "IT-NO": 0}, "powerExportBreakdown": {"BE": 529, "CH": 821, "DE": 2079, "ES": 0, "GB": 1601, "IT-NO": 261}, "fossilFreePercentage": 99, "renewablePercentage": 38, "powerConsumptionTotal": 39694, "powerProductionTotal": 45462, "powerImportTotal": 1178, "powerExportTotal": 5290, "isEstimated": false, "estimationMethod": null}, {"zone": "FR", "datetime": "2025-05-31T15:00:00.000Z", "updatedAt": "2025-05-31T15:43:24.565Z", "createdAt": "2025-05-28T15:45:05.170Z", "powerConsumptionBreakdown": {"nuclear": 24206, "geothermal": 0, "biomass": 848, "coal": 6, "wind": 1385, "solar": 8451, "hydro": 4409, "gas": 445, "oil": 69, "unknown": 2, "hydro discharge": 0, "battery discharge": 0}, "powerProductionBreakdown": {"nuclear": 28136, "geothermal": null, "biomass": 973, "coal": 0, "wind": 1546, "solar": 9252, "hydro": 5103, "gas": 373, "oil": 79, "unknown": null, "hydro discharge": -1652, "battery discharge": -3}, "powerImportBreakdown": {"BE": 0, "CH": 0, "DE": 0, "ES": 1178, "GB": 0, "IT-NO": 0}, "powerExportBreakdown": {"BE": 529, "CH": 821, "DE": 1969, "ES": 0, "GB": 1601, "IT-NO": 244}, "fossilFreePercentage": 99, "renewablePercentage": 38, "powerConsumptionTotal": 39821, "powerProductionTotal": 45462, "powerImportTotal": 1178, "powerExportTotal": 5163, "isEstimated": true, "estimationMethod": "TIME_SLICER_AVERAGE"}, {"zone": "FR", "datetime": "2025-05-31T16:00:00.000Z", "updatedAt": "2025-05-31T15:43:24.565Z", "createdAt": "2025-05-28T16:41:01.098Z", "powerConsumptionBreakdown": {"nuclear": 26126, "geothermal": 0, "biomass": 856, "coal": 8, "wind": 2275, "solar": 7202, "hydro": 4873, "gas": 489, "oil": 70, "unknown": 3, "hydro discharge": 0, "battery discharge": 0}, "powerProductionBreakdown": {"nuclear": 30354, "geothermal": null, "biomass": 977, "coal": 0, "wind": 2524, "solar": 7589, "hydro": 5624, "gas": 374, "oil": 79, "unknown": null, "hydro discharge": -735, "battery discharge": -7}, "powerImportBreakdown": {"BE": 0, "CH": 0, "DE": 0, "ES": 1621, "GB": 0, "IT-NO": 0}, "powerExportBreakdown": {"BE": 1166, "CH": 416, "DE": 2168, "ES": 0, "GB": 1978, "IT-NO": 771}, "fossilFreePercentage": 99, "renewablePercentage": 36, "powerConsumptionTotal": 41901, "powerProductionTotal": 47520, "powerImportTotal": 1621, "powerExportTotal": 6498, "isEstimated": true, "estimationMethod": "TIME_SLICER_AVERAGE"}]}